[
  {
    "id": "tag:google.com,2013:googlealerts/feed:4949351782572842671",
    "title": "3/11上市外資買超排行前20名| MoneyDJ理財網 - LINE TODAY",
    "link": "https://www.google.com/url?rct=j&sa=t&url=https://today.line.me/tw/v3/article/gz8O2Ng&ct=ga&cd=CAIyHTI1ZGU5MDQ5NWZhNGM3ZGQ6Y29tOnpoLVRXOlRX&usg=AOvVaw3MGztgoEk1KSM56fhKwTOt",
    "published": "2026-03-12T01:36:49Z",
    "summary": "... <b>3231緯創</b>9,334 133.00 4.00 19 00982A主動群益台灣強棒9,262 16.19 0.76 20 2481強茂9,173 91.80 8.30 資料來源-MoneyDJ理財網 &middot; 查看原始文章 &middot; #富邦科技",
    "stock_id": "3231",
    "name": "緯創",
    "fetched_at": "2026-03-12T03:33:40.489313+00:00"
  },
  {
    "id": "tag:google.com,2013:googlealerts/feed:14020663823236108591",
    "title": "要當董事的小散戶才有錢賺 - 理財寶",
    "link": "https://www.google.com/url?rct=j&sa=t&url=https://www.cmoney.tw/forum/article/177078211&ct=ga&cd=CAIyHTI1ZGU5MDQ5NWZhNGM3ZGQ6Y29tOnpoLVRXOlRX&usg=AOvVaw3AXK8DC23g-TPZoJlF_8Sf",
    "published": "2026-03-12T00:28:52Z",
    "summary": "<b>緯創</b>. <b>3231</b>. 133. 4 (+3.10%). 最新時事. 5 天前 投資網誌. 【即時新聞】<b>緯創</b>2月營收狂飆2848億創新高，AI伺服器帶動年增177% &middot; 6 天前 投資網誌. 【美股焦點】不&nbsp;...",
    "stock_id": "3231",
    "name": "緯創",
    "fetched_at": "2026-03-12T03:33:40.489324+00:00"
  },
  {
    "id": "tag:google.com,2013:googlealerts/feed:7940983111024192165",
    "title": "黃仁勳GTC前5層蛋糕理論台廠17強出陣 - Yahoo新聞",
    "link": "https://www.google.com/url?rct=j&sa=t&url=https://tw.news.yahoo.com/%25E9%25BB%2583%25E4%25BB%2581%25E5%258B%25B3gtc%25E5%2589%258D5%25E5%25B1%25A4%25E8%259B%258B%25E7%25B3%2595%25E7%2590%2586%25E8%25AB%2596-%25E5%258F%25B0%25E5%25BB%25A017%25E5%25BC%25B7%25E5%2587%25BA%25E9%2599%25A3-160500665.html&ct=ga&cd=CAIyHTI1ZGU5MDQ5NWZhNGM3ZGQ6Y29tOnpoLVRXOlRX&usg=AOvVaw0fcUd4btaZJRlfYUQfZvuL",
    "published": "2026-03-12T00:24:17Z",
    "summary": "相關台廠包括廣達（2382）、<b>緯創</b>（<b>3231</b>）、緯穎（6669）、奇鋐（3017）與雙鴻（3324）等，均在AI伺服器整機或散熱系統領域扮演重要角色。 AI 模型推論帶動機器人與自駕落地.",
    "stock_id": "3231",
    "name": "緯創",
    "fetched_at": "2026-03-12T03:33:40.489329+00:00"
  },
  {
    "id": "tag:google.com,2013:googlealerts/feed:1461985840050622898",
    "title": "大漲千點為何帶賣股? 台積電鴻海<b>緯創</b>如何做? 【雙鍵第2】目標翻倍 - 鉅亨網",
    "link": "https://www.google.com/url?rct=j&sa=t&url=https://news.cnyes.com/news/id/6378403&ct=ga&cd=CAIyHTI1ZGU5MDQ5NWZhNGM3ZGQ6Y29tOnpoLVRXOlRX&usg=AOvVaw1aKWT2fJAQm68sFsnV7Snw",
    "published": "2026-03-12T00:01:04Z",
    "summary": "台積電(2330-TW) <b>緯創</b>(<b>3231</b>-TW) 鴻海(2317-TW) 廣達(2382-TW) 買點， 奇鋐(3017-TW)， 鴻海(2317-TW) 不要買太早? 以上六檔如何買賣? 點下面YT 頻道訂閱連結&nbsp;...",
    "stock_id": "3231",
    "name": "緯創",
    "fetched_at": "2026-03-12T03:33:40.489333+00:00"
  },
  {
    "id": "tag:google.com,2013:googlealerts/feed:8111511490216542319",
    "title": "【台股2月營收表現速覽】營收創高、成長、衰退股清單 - CMoney投資網誌",
    "link": "https://www.google.com/url?rct=j&sa=t&url=https://cmnews.com.tw/article/cmoney-4c8a3e8f-1d30-11f1-8f45-74b714f64217&ct=ga&cd=CAIyHTI1ZGU5MDQ5NWZhNGM3ZGQ6Y29tOnpoLVRXOlRX&usg=AOvVaw3w6nYZfq_gZ-kYjFcGZ8Fz",
    "published": "2026-03-11T23:57:44Z",
    "summary": "<b>緯創</b>(<b>3231</b>) &middot; 鈺創(5351) &middot; 群聯(8299) &middot; 宜鼎(5289) &middot; 至上(8112). 《營收飆漲追蹤器》APP，秒速接收你關注的公司營收資訊，潛力股一次掌握 手機點我下載  https&nbsp;...",
    "stock_id": "3231",
    "name": "緯創",
    "fetched_at": "2026-03-12T03:33:40.489337+00:00"
  },
  {
    "id": "tag:google.com,2013:googlealerts/feed:2515944323029161297",
    "title": "《外資》買超股：中華電、仁寶、技嘉- 上市櫃- 旺得富理財網",
    "link": "https://www.google.com/url?rct=j&sa=t&url=https://wantrich.chinatimes.com/news/20260312900022-420101&ct=ga&cd=CAIyHTI1ZGU5MDQ5NWZhNGM3ZGQ6Y29tOnpoLVRXOlRX&usg=AOvVaw1itCH3Aq8FLY9IGnsW6iNK",
    "published": "2026-03-11T23:51:33Z",
    "summary": "... <b>緯創</b>(<b>3231</b>) 宏捷科(8086). 微星(2377) 大同(2371) 矽格(6257) 旺宏(2337) 智冠(5478). 萬海(2615) 長榮航(2618) 華榮(1608) 台船(2208) 益航(2601). 大成鋼&nbsp;...",
    "stock_id": "3231",
    "name": "緯創",
    "fetched_at": "2026-03-12T03:33:40.489341+00:00"
  },
  {
    "id": "tag:google.com,2013:googlealerts/feed:12121616162524753910",
    "title": "AI機櫃需求強！大摩首選台系ODM三雄<b>緯創</b>「目標價喊上215元」2月營收年增177%",
    "link": "https://www.google.com/url?rct=j&sa=t&url=https://tw.stock.yahoo.com/news/ai%25E6%25A9%259F%25E6%25AB%2583%25E9%259C%2580%25E6%25B1%2582%25E5%25BC%25B7-%25E5%25A4%25A7%25E6%2591%25A9%25E9%25A6%2596%25E9%2581%25B8%25E5%258F%25B0%25E7%25B3%25BBodm%25E4%25B8%2589%25E9%259B%2584-%25E7%25B7%25AF%25E5%2589%25B5-%25E7%259B%25AE%25E6%25A8%2599%25E5%2583%25B9%25E5%2596%258A%25E4%25B8%258A215%25E5%2585%2583-2%25E6%259C%2588%25E7%2587%259F%25E6%2594%25B6%25E5%25B9%25B4%25E5%25A2%259E177-224000656.html&ct=ga&cd=CAIyHTI1ZGU5MDQ5NWZhNGM3ZGQ6Y29tOnpoLVRXOlRX&usg=AOvVaw1oRs-KoY1IYkFul_nsWNB7",
    "published": "2026-03-11T23:20:56Z",
    "summary": "在AI伺服器基礎建設需求擴張帶動下，大摩看好台系ODM廠表現，其中偏好順序為<b>緯創</b>（<b>3231</b>）、鴻海（2317）與廣達（2382）。",
    "stock_id": "3231",
    "name": "緯創",
    "fetched_at": "2026-03-12T03:33:40.489345+00:00"
  },
  {
    "id": "tag:google.com,2013:googlealerts/feed:13057305618438330296",
    "title": "甲骨文上調展望…台鏈沾光鴻海、廣達、<b>緯創</b>等受惠",
    "link": "https://www.google.com/url?rct=j&sa=t&url=https://tw.news.yahoo.com/%25E7%2594%25B2%25E9%25AA%25A8%25E6%2596%2587%25E4%25B8%258A%25E8%25AA%25BF%25E5%25B1%2595%25E6%259C%259B-%25E5%258F%25B0%25E9%258F%2588%25E6%25B2%25BE%25E5%2585%2589-%25E9%25B4%25BB%25E6%25B5%25B7-%25E5%25BB%25A3%25E9%2581%2594-%25E7%25B7%25AF%25E5%2589%25B5%25E7%25AD%2589%25E5%258F%2597%25E6%2583%25A0-225002363.html&ct=ga&cd=CAIyHTI1ZGU5MDQ5NWZhNGM3ZGQ6Y29tOnpoLVRXOlRX&usg=AOvVaw2uRRo-8eAECCkBXrJK-_jY",
    "published": "2026-03-11T23:08:20Z",
    "summary": "<b>緯創</b>. <b>3231</b>.TW. 133.0(3.10%) &middot; ORCL. 163.12(9.18%) &middot; 601138.SS. 53.89(0.86%). 雲端巨頭甲骨文（Oracle）10日公布上季財報與本季財測均優於華爾街預期，並上調&nbsp;...",
    "stock_id": "3231",
    "name": "緯創",
    "fetched_at": "2026-03-12T03:33:40.489349+00:00"
  },
  {
    "id": "tag:google.com,2013:googlealerts/feed:10646860855328408974",
    "title": "1表看》鴻海、廣達及時雨來了？才說AI下游無亮點「大咖投顧上修伺服器出貨」點名<b>緯創</b>、創意",
    "link": "https://www.google.com/url?rct=j&sa=t&url=https://wantrich.chinatimes.com/news/20260312900007-420101&ct=ga&cd=CAIyHTI1ZGU5MDQ5NWZhNGM3ZGQ6Y29tOnpoLVRXOlRX&usg=AOvVaw2qLZwkeHPNH7nd-uXERHF9",
    "published": "2026-03-11T22:23:23Z",
    "summary": "... 的7萬台上修至7.5萬台，點名看好鴻海(2317)、緯穎(6669)、廣達(2382)及<b>緯創</b>(<b>3231</b>)等14檔重點標的。本土金控一...",
    "stock_id": "3231",
    "name": "緯創",
    "fetched_at": "2026-03-12T03:33:40.489353+00:00"
  },
  {
    "id": "tag:google.com,2013:googlealerts/feed:7550932066849177933",
    "title": "大摩看好GB200/300 NVL72 機櫃2月出貨量按讚三台廠 - 國泰證券",
    "link": "https://www.google.com/url?rct=j&sa=t&url=https://www.cathaysec.com.tw/cathaysec/News/nContent.aspx%3FNewsDate%3D20260311%26CSeqNO%3DE9373911&ct=ga&cd=CAIyHTI1ZGU5MDQ5NWZhNGM3ZGQ6Y29tOnpoLVRXOlRX&usg=AOvVaw0-xeVG7xS4owZfteK6KGP_",
    "published": "2026-03-11T22:18:02Z",
    "summary": "展望全年，預估2026年出貨量將達7萬至8萬台，較去年大幅倍增，按讚<b>緯創</b>（<b>3231</b>）、鴻海（2317）、廣達（2382）三台廠。 總產出上看6,500台但有這個變數 針對&nbsp;...",
    "stock_id": "3231",
    "name": "緯創",
    "fetched_at": "2026-03-12T03:33:40.489356+00:00"
  },
  {
    "id": "tag:google.com,2013:googlealerts/feed:15196548887073416308",
    "title": "黃仁勳GTC前5層蛋糕理論台廠17強出陣 - 三立iNEWS",
    "link": "https://www.google.com/url?rct=j&sa=t&url=https://inews.setn.com/news/1805963&ct=ga&cd=CAIyHTI1ZGU5MDQ5NWZhNGM3ZGQ6Y29tOnpoLVRXOlRX&usg=AOvVaw0ZhRD4sQUMIwBd28mW5QrJ",
    "published": "2026-03-11T22:07:01Z",
    "summary": "... 緯創等因伺服器與散熱需求大增而受惠。模型層雖以美商主導，但AI ... 相關台廠包括廣達（2382）、<b>緯創</b>（<b>3231</b>）、緯穎（6669）、奇鋐（3017）與雙&nbsp;...",
    "stock_id": "3231",
    "name": "緯創",
    "fetched_at": "2026-03-12T03:33:40.489360+00:00"
  },
  {
    "id": "tag:google.com,2013:googlealerts/feed:5045482954914501476",
    "title": "2303 聯電- 【03/10 自營商買超排行榜】",
    "link": "https://www.google.com/url?rct=j&sa=t&url=https://www.cmoney.tw/forum/article/177333278&ct=ga&cd=CAIyHTI1ZGU5MDQ5NWZhNGM3ZGQ6Y29tOnpoLVRXOlRX&usg=AOvVaw3X1-8-76nr-bX-8IJ7yCax",
    "published": "2026-03-11T21:29:00Z",
    "summary": "文中還提及：仁寶(2324)、 至上(8112)、 <b>緯創</b>(<b>3231</b>)、 華泰(2329)。今日自營商買超張數最多的個股是...-1.聯電(2303)：1782 *連續3日買超2.",
    "stock_id": "3231",
    "name": "緯創",
    "fetched_at": "2026-03-12T03:33:40.489364+00:00"
  },
  {
    "id": "tag:google.com,2013:googlealerts/feed:16323425192325758168",
    "title": "【美股焦點】軟體被打趴、硬體翻身：AI資金突然大換邊！",
    "link": "https://www.google.com/url?rct=j&sa=t&url=https://cmnews.com.tw/article/josh-83b4f090-1d2b-11f1-b4ae-7663e69ba29a&ct=ga&cd=CAIyHTI1ZGU5MDQ5NWZhNGM3ZGQ6Y29tOnpoLVRXOlRX&usg=AOvVaw3qptovXp5fXgnnRFG_uRsK",
    "published": "2026-03-11T21:23:53Z",
    "summary": "<b>緯創</b>(<b>3231</b>) &middot; 群聯(8299) &middot; 威剛(3260) &middot; 南亞科(2408) &middot; 台達電(2308) &middot; 奇鋐(3017). 手機爆容量的真實焦慮. 台北時間2026/3/11 清晨（美股3/10 交易日），你可能&nbsp;...",
    "stock_id": "3231",
    "name": "緯創",
    "fetched_at": "2026-03-12T03:33:40.489367+00:00"
  },
  {
    "id": "tag:google.com,2013:googlealerts/feed:15933897087118329489",
    "title": "自營商砸1.7億加碼5千張！這「面板廠」全年維持獲利超額配息1元| FTNN 新聞網",
    "link": "https://www.google.com/url?rct=j&sa=t&url=https://www.ftnn.com.tw/news/529195&ct=ga&cd=CAIyHTI1ZGU5MDQ5NWZhNGM3ZGQ6Y29tOnpoLVRXOlRX&usg=AOvVaw258L2c-kjSsZrq2HVYpyoW",
    "published": "2026-03-11T21:00:50Z",
    "summary": "... <b>緯創</b>（<b>3231</b>），買超1,567張；第五名、聯電（2303），買超1,475張。 廣告更多內容請繼續往下閱讀. 往後，第六名、旺宏（2337），買超1,074張；第七名、至上&nbsp;...",
    "stock_id": "3231",
    "name": "緯創",
    "fetched_at": "2026-03-12T03:33:40.489371+00:00"
  },
  {
    "id": "tag:google.com,2013:googlealerts/feed:13391723419495345760",
    "title": "鴻海、廣達、<b>緯創</b>等老AI 股不隨大盤回春出了什麼問題？ - 國泰證券",
    "link": "https://www.google.com/url?rct=j&sa=t&url=https://www.cathaysec.com.tw/cathaysec/News/nContent.aspx%3FNewsDate%3D20260311%26CSeqNO%3DE9374518&ct=ga&cd=CAIyHTI1ZGU5MDQ5NWZhNGM3ZGQ6Y29tOnpoLVRXOlRX&usg=AOvVaw2wIJ42CXrL3q6ViJuReiYv",
    "published": "2026-03-11T20:58:08Z",
    "summary": "近日全球股市受中東戰爭影響，震盪十分劇烈，而在震盪過程中，不少強勢股雖從高檔回落，但盤勢一回穩便再度反彈；反觀鴻海（2317）、廣達（2382）、<b>緯創</b>（<b>3231</b>）等ODM&nbsp;...",
    "stock_id": "3231",
    "name": "緯創",
    "fetched_at": "2026-03-12T03:33:40.489374+00:00"
  },
  {
    "id": "tag:google.com,2013:googlealerts/feed:5751322348081778251",
    "title": "三大法人砸517億大舉搶進！台股漲破1300點光復3萬4大關股民笑：散戶團結小兒求饒",
    "link": "https://www.google.com/url?rct=j&sa=t&url=https://www.ftnn.com.tw/news/529165&ct=ga&cd=CAIyHTI1ZGU5MDQ5NWZhNGM3ZGQ6Y29tOnpoLVRXOlRX&usg=AOvVaw3JnpsNPrY3AJf0dO3wgIZU",
    "published": "2026-03-11T20:49:35Z",
    "summary": "AI族群方面，指標股英業達（2356）上漲2.1元，漲幅5.13%，收43元；<b>緯創</b>（<b>3231</b>）上漲4元，漲幅3.1%，收133元；至於其他AI股方面，宏碁（2353）上漲1元&nbsp;...",
    "stock_id": "3231",
    "name": "緯創",
    "fetched_at": "2026-03-12T03:33:40.489378+00:00"
  },
  {
    "id": "tag:google.com,2013:googlealerts/feed:758434393347341156",
    "title": "大摩看好GB200/300 NVL72機櫃2月出貨量按讚三台廠 - UDN",
    "link": "https://www.google.com/url?rct=j&sa=t&url=https://udn.com/news/story/7253/9373911&ct=ga&cd=CAIyHTI1ZGU5MDQ5NWZhNGM3ZGQ6Y29tOnpoLVRXOlRX&usg=AOvVaw007FJqibTu9BvPDRqab0V7",
    "published": "2026-03-11T19:09:19Z",
    "summary": "展望全年，預估2026年出貨量將達7萬至8萬台，較去年大幅倍增，按讚<b>緯創</b>（<b>3231</b>）、鴻海（2317）、廣達（2382）三台廠。 總產出上看6,500台但有這個變數. 針對&nbsp;...",
    "stock_id": "3231",
    "name": "緯創",
    "fetched_at": "2026-03-12T03:33:40.489382+00:00"
  },
  {
    "id": "tag:google.com,2013:googlealerts/feed:13379744426693989089",
    "title": "《DJ在線》CSP加碼AI，伺服器ODM續擴資本支出| MoneyDJ理財網 - LINE TODAY",
    "link": "https://www.google.com/url?rct=j&sa=t&url=https://today.line.me/tw/v3/article/8nqxQmE&ct=ga&cd=CAIyHTI1ZGU5MDQ5NWZhNGM3ZGQ6Y29tOnpoLVRXOlRX&usg=AOvVaw28K99puQElBlUfNIf5zgSN",
    "published": "2026-03-11T18:04:37Z",
    "summary": "掌握多家GPU大廠AI伺服器零組件及系統的<b>緯創</b>(<b>3231</b>)，先前提到今年資本支出將以台灣為最大投資重心，預計超過一半支出落在台灣，其中北部新竹與湖口為主要&nbsp;...",
    "stock_id": "3231",
    "name": "緯創",
    "fetched_at": "2026-03-12T03:33:40.489385+00:00"
  },
  {
    "id": "tag:google.com,2013:googlealerts/feed:18446183025461883403",
    "title": "<b>緯創</b>技術分析: 行事曆研究報告<b>緯創</b>2025K線圖日線週線月線還原日線",
    "link": "https://www.google.com/url?rct=j&sa=t&url=https://miracledental.com.tw/miracledental/52a71d/2025-%25E7%25B7%25AF/dd4fe4&ct=ga&cd=CAIyHTI1ZGU5MDQ5NWZhNGM3ZGQ6Y29tOnpoLVRXOlRX&usg=AOvVaw3fWxk2NsTmz8lSIECHCxvl",
    "published": "2026-03-11T17:51:23Z",
    "summary": "... 緯創集團旗下子公司20250611 TWSE HOT 年終6 iul 2025 WISTRON CORPORATION 最新股價技術分析K線走勢圖即時漲跌雙鴻2025 <b>緯創3231</b>技術線圖技術線圖ADO指標&nbsp;...",
    "stock_id": "3231",
    "name": "緯創",
    "fetched_at": "2026-03-12T03:33:40.489389+00:00"
  },
  {
    "id": "tag:google.com,2013:googlealerts/feed:8689829430680696746",
    "title": "鴻海、廣達、<b>緯創</b>等老AI 股不隨大盤回春出了什麼問題？",
    "link": "https://www.google.com/url?rct=j&sa=t&url=https://money.udn.com/money/story/5607/9374518&ct=ga&cd=CAIyHTI1ZGU5MDQ5NWZhNGM3ZGQ6Y29tOnpoLVRXOlRX&usg=AOvVaw1xu_TvUbzuMabx80GikcKW",
    "published": "2026-03-11T16:24:20Z",
    "summary": "近日全球股市受中東戰爭影響，震盪十分劇烈，而在震盪過程中，不少強勢股雖從高檔回落，但盤勢一回穩便再度反彈；反觀鴻海（2317）、廣達（2382）、<b>緯創</b>（<b>3231</b>）等ODM廠&nbsp;...",
    "stock_id": "3231",
    "name": "緯創",
    "fetched_at": "2026-03-12T03:33:40.489393+00:00"
  },
  {
    "id": "tag:google.com,2013:googlealerts/feed:6022350300583252178",
    "title": "AI機櫃需求強！大摩首選台系ODM三雄<b>緯創</b>「目標價喊上2...｜CMoney 股市爆料同學會",
    "link": "https://www.google.com/url?rct=j&sa=t&url=https://www.cmoney.tw/forum/article/177380817&ct=ga&cd=CAIyHTI1ZGU5MDQ5NWZhNGM3ZGQ6Y29tOnpoLVRXOlRX&usg=AOvVaw0GtuGfyFBivHX8QiMeCALt",
    "published": "2026-03-12T04:39:39Z",
    "summary": "<b>緯創</b>. <b>3231</b>. 129. 1.5 (+1.18%). 最新時事. 18 小時前 投資網誌. 【台股2月營收表現速覽】營收創高、成長、衰退股清單 &middot; 18 小時前 投資網誌. 【美股焦點】軟體&nbsp;...",
    "stock_id": "3231",
    "name": "緯創",
    "fetched_at": "2026-03-12T05:55:23.494655+00:00"
  },
  {
    "id": "tag:google.com,2013:googlealerts/feed:4481935986025867251",
    "title": "<b>3231 緯創</b>- 預計回測125。再看要彈還是吃屎｜CMoney 股市爆料同學會 - 理財寶",
    "link": "https://www.google.com/url?rct=j&sa=t&url=https://www.cmoney.tw/forum/article/177379504&ct=ga&cd=CAIyHTI1ZGU5MDQ5NWZhNGM3ZGQ6Y29tOnpoLVRXOlRX&usg=AOvVaw20cBKjUA7ZBmhZ6maqmbmc",
    "published": "2026-03-12T03:29:39Z",
    "summary": "<b>3231</b>. 133. 4 (+3.10%). 最新時事. 5 天前 投資網誌. 【即時新聞】<b>緯創</b>2月營收 ... <b>緯創</b>. 籌碼換手，過程很慢，但你若從一月觀察至今，是往好的方向整理的&nbsp;...",
    "stock_id": "3231",
    "name": "緯創",
    "fetched_at": "2026-03-12T05:55:23.494667+00:00"
  },
  {
    "id": "tag:google.com,2013:googlealerts/feed:1809842661270643425",
    "title": "<b>緯創</b>公告本公司董事會通過114年度合併財務報告 - MoneyDJ理財網",
    "link": "https://www.google.com/url?rct=j&sa=t&url=https://www.moneydj.com/kmdj/news/newsviewer.aspx%3Fa%3D0f3d6948-468f-4737-89ee-229112f436c8&ct=ga&cd=CAIyHTI1ZGU5MDQ5NWZhNGM3ZGQ6Y29tOnpoLVRXOlRX&usg=AOvVaw0He3aGXsu_UIFjEUWfy5dN",
    "published": "2026-03-12T10:26:46Z",
    "summary": "公開資訊觀測站重大訊息公告 (<b>3231</b>)<b>緯創</b>-公告本公司董事會通過114年度合併財務報告 1.提報董事會或經董事會決議日期:115/03/12",
    "stock_id": "3231",
    "name": "緯創",
    "fetched_at": "2026-03-12T14:05:30.233666+00:00"
  },
  {
    "id": "tag:google.com,2013:googlealerts/feed:11747386418706410701",
    "title": "<b>緯創</b>每股擬配發現金股利5.5元殖利率約4.15% - Yahoo股市",
    "link": "https://www.google.com/url?rct=j&sa=t&url=https://tw.stock.yahoo.com/news/%25E7%25B7%25AF%25E5%2589%25B5%25E6%25AF%258F%25E8%2582%25A1%25E6%2593%25AC%25E9%2585%258D%25E7%2599%25BC%25E7%258F%25BE%25E9%2587%2591%25E8%2582%25A1%25E5%2588%25A955%25E5%2585%2583-%25E6%25AE%2596%25E5%2588%25A9%25E7%258E%2587%25E7%25B4%2584415-101151304.html&ct=ga&cd=CAIyHTI1ZGU5MDQ5NWZhNGM3ZGQ6Y29tOnpoLVRXOlRX&usg=AOvVaw0IKOmWP3bHHgxrJH6PdhaH",
    "published": "2026-03-12T10:22:56Z",
    "summary": "代工大廠<b>緯創</b>（<b>3231</b>）今（12）日召開董事會，會中通過114年度財務報告。公布去年每股盈餘（EPS）為9.04元，董事會決議每股配發現金股利5.5元，以今日收盤價計算，&nbsp;...",
    "stock_id": "3231",
    "name": "緯創",
    "fetched_at": "2026-03-12T14:05:30.233676+00:00"
  },
  {
    "id": "tag:google.com,2013:googlealerts/feed:6659998120697793119",
    "title": "<b>緯創</b>:董事會決議辦理現金增資發行普通股參與發行海外存託憑證 - 鉅亨網",
    "link": "https://www.google.com/url?rct=j&sa=t&url=https://news.cnyes.com/news/id/6381563&ct=ga&cd=CAIyHTI1ZGU5MDQ5NWZhNGM3ZGQ6Y29tOnpoLVRXOlRX&usg=AOvVaw1l8k3LIGFyliAi_mNcYvlY",
    "published": "2026-03-12T10:16:31Z",
    "summary": "第11款. 公司代號：<b>3231</b>. ‌. 公司名稱：<b>緯創</b> 發言日期：2026/03/12 發言時間：17:59:24 發言人：石慶堂. 1.董事會決議日期:115/03/12.",
    "stock_id": "3231",
    "name": "緯創",
    "fetched_at": "2026-03-12T14:05:30.233681+00:00"
  },
  {
    "id": "tag:google.com,2013:googlealerts/feed:10552426396616541902",
    "title": "<b>緯創</b>:董事會決議以私募方式辦理現金增資發行普通股及/或以私募方式發行新股參與海外存託 ...",
    "link": "https://www.google.com/url?rct=j&sa=t&url=https://news.cnyes.com/news/id/6381562&ct=ga&cd=CAIyHTI1ZGU5MDQ5NWZhNGM3ZGQ6Y29tOnpoLVRXOlRX&usg=AOvVaw2ufPaUdfTgAqpWF-H_bBTN",
    "published": "2026-03-12T10:16:19Z",
    "summary": "第11款. 公司代號：<b>3231</b>. ‌. 公司名稱：<b>緯創</b> 發言日期：2026/03/12 發言時間：18:00:26 發言人：石慶堂. 1.董事會決議日期:115/03/12.",
    "stock_id": "3231",
    "name": "緯創",
    "fetched_at": "2026-03-12T14:05:30.233686+00:00"
  },
  {
    "id": "tag:google.com,2013:googlealerts/feed:2591072690348478169",
    "title": "《熱門族群》低軌衛星又火了！2檔鎖漲停群創法說前爆量噴 - Yahoo股市",
    "link": "https://www.google.com/url?rct=j&sa=t&url=https://tw.stock.yahoo.com/news/%25E7%2586%25B1%25E9%2596%2580%25E6%2597%258F%25E7%25BE%25A4-%25E4%25BD%258E%25E8%25BB%258C%25E8%25A1%259B%25E6%2598%259F%25E5%258F%2588%25E7%2581%25AB%25E4%25BA%2586-2%25E6%25AA%2594%25E9%258E%2596%25E6%25BC%25B2%25E5%2581%259C-%25E7%25BE%25A4%25E5%2589%25B5%25E6%25B3%2595%25E8%25AA%25AA%25E5%2589%258D%25E7%2588%2586%25E9%2587%258F%25E5%2599%25B4-023926160.html&ct=ga&cd=CAIyHTI1ZGU5MDQ5NWZhNGM3ZGQ6Y29tOnpoLVRXOlRX&usg=AOvVaw3S3g785Y7Lr-omiNGYZxre",
    "published": "2026-03-12T10:15:58Z",
    "summary": "<b>緯創</b>. <b>3231</b>.TW. 132.5(0.38%) &middot; 欣興. 3037.TW. 480.0(3.00%) &middot; CL=F. 91.03(4.33%). 【時報-台北電】受累中東戰事餘波盪漾，油價急升7%衝擊，美亞歐股&nbsp;...",
    "stock_id": "3231",
    "name": "緯創",
    "fetched_at": "2026-03-12T14:05:30.233690+00:00"
  },
  {
    "id": "tag:google.com,2013:googlealerts/feed:3143852385745137922",
    "title": "3萬4大關得而復失三大法人狂捲811億離場！股民崩潰：全軍覆沒四大皆空 - FTNN 新聞網",
    "link": "https://www.google.com/url?rct=j&sa=t&url=https://www.ftnn.com.tw/news/529471&ct=ga&cd=CAIyHTI1ZGU5MDQ5NWZhNGM3ZGQ6Y29tOnpoLVRXOlRX&usg=AOvVaw0GZeJELD3oAc-Jg3jyBNc9",
    "published": "2026-03-12T10:02:16Z",
    "summary": "AI族群方面，指標股英業達（2356）下跌0.05元，跌幅0.12%，收42.95元；<b>緯創</b>（<b>3231</b>）下跌0.5元，跌幅0.38%，收132.5元；至於其他AI股方面，宏碁（2353）上漲&nbsp;...",
    "stock_id": "3231",
    "name": "緯創",
    "fetched_at": "2026-03-12T14:05:30.233694+00:00"
  },
  {
    "id": "tag:google.com,2013:googlealerts/feed:1325290176558084829",
    "title": "互聯網、遊戲、半導體動能加持，緯軟今年營收、獲利持續看增 - Yahoo股市",
    "link": "https://www.google.com/url?rct=j&sa=t&url=https://tw.stock.yahoo.com/news/%25E4%25BA%2592%25E8%2581%25AF%25E7%25B6%25B2-%25E9%2581%258A%25E6%2588%25B2-%25E5%258D%258A%25E5%25B0%258E%25E9%25AB%2594%25E5%258B%2595%25E8%2583%25BD%25E5%258A%25A0%25E6%258C%2581-%25E7%25B7%25AF%25E8%25BB%259F%25E4%25BB%258A%25E5%25B9%25B4%25E7%2587%259F%25E6%2594%25B6-%25E7%258D%25B2%25E5%2588%25A9%25E6%258C%2581%25E7%25BA%258C%25E7%259C%258B%25E5%25A2%259E-085659495.html&ct=ga&cd=CAIyHTI1ZGU5MDQ5NWZhNGM3ZGQ6Y29tOnpoLVRXOlRX&usg=AOvVaw3Wxf3WfIcDYOu3F-gP0DSE",
    "published": "2026-03-12T09:30:08Z",
    "summary": "<b>緯創</b>. <b>3231</b>.TW. 132.5(0.38%). 【財訊快報／記者陳浩寧報導】緯軟(4953)2025年營運回溫，獲利寫下歷史次高，EPS達8.45元。展望今年，董事長蕭清志表示，去年&nbsp;...",
    "stock_id": "3231",
    "name": "緯創",
    "fetched_at": "2026-03-12T14:05:30.233698+00:00"
  },
  {
    "id": "tag:google.com,2013:googlealerts/feed:2267738113029544596",
    "title": "2330 台積電- 早盤如果你有守住獲利，心態一定很從容",
    "link": "https://www.google.com/url?rct=j&sa=t&url=https://www.cmoney.tw/forum/article/177388586&ct=ga&cd=CAIyHTI1ZGU5MDQ5NWZhNGM3ZGQ6Y29tOnpoLVRXOlRX&usg=AOvVaw0vcuxnlpLn7pH1YT6jINcy",
    "published": "2026-03-12T08:14:26Z",
    "summary": "文中還提及：嘉澤(3533)、 鈺創(5351)、 <b>緯創</b>(<b>3231</b>)、 日月光投控(3711)。各位朋友午安好！我是沈爸。今天（3/12）大盤的走勢，完全印證了沈爸盤前跟大家預警&nbsp;...",
    "stock_id": "3231",
    "name": "緯創",
    "fetched_at": "2026-03-12T14:05:30.233702+00:00"
  },
  {
    "id": "tag:google.com,2013:googlealerts/feed:17572084849580616690",
    "title": "自營商砸1.7億加碼5千張！這「面板廠」全年維持獲利超額配息1元 - Yahoo股市",
    "link": "https://www.google.com/url?rct=j&sa=t&url=https://tw.stock.yahoo.com/news/%25E8%2587%25AA%25E7%2587%259F%25E5%2595%2586%25E7%25A0%25B81-7%25E5%2584%2584%25E5%258A%25A0%25E7%25A2%25BC5%25E5%258D%2583%25E5%25BC%25B5-%25E9%2580%2599-%25E9%259D%25A2%25E6%259D%25BF%25E5%25BB%25A0-%25E5%2585%25A8%25E5%25B9%25B4%25E7%25B6%25AD%25E6%258C%2581%25E7%258D%25B2%25E5%2588%25A9-150000611.html&ct=ga&cd=CAIyHTI1ZGU5MDQ5NWZhNGM3ZGQ6Y29tOnpoLVRXOlRX&usg=AOvVaw1sJjSrRRkg_opcc6KK2t0q",
    "published": "2026-03-12T08:11:03Z",
    "summary": "... <b>緯創</b>（<b>3231</b>），買超1,567張；第五名、聯電（2303），買超1,475張。 廣告. 廣告. 往後，第六名、旺宏（2337），買超1,074張；第七名、至上（8112），買超931張&nbsp;...",
    "stock_id": "3231",
    "name": "緯創",
    "fetched_at": "2026-03-12T14:05:30.233706+00:00"
  },
  {
    "id": "tag:google.com,2013:googlealerts/feed:16371771808073429607",
    "title": "近期召開國內、外法說會之上市櫃公司一覽表_富聯網",
    "link": "https://www.google.com/url?rct=j&sa=t&url=https://ww2.money-link.com.tw/RealtimeNews/NewsContent.aspx%3FSN%3D2335494002%26PU%3D0010&ct=ga&cd=CAIyHTI1ZGU5MDQ5NWZhNGM3ZGQ6Y29tOnpoLVRXOlRX&usg=AOvVaw1cRzQhEKqEwuw0-Gxt16py",
    "published": "2026-03-12T07:24:36Z",
    "summary": "... <b>緯創</b>(<b>3231</b>)、台產(2832)、華通(2313)、晶碩(6491)、凱衛(5201)、聚陽(1477)、微星(2377)、聯強(2347)、中傑-KY(6965)、旭隼(6409)、全科(3209)、台燿(6274)&nbsp;...",
    "stock_id": "3231",
    "name": "緯創",
    "fetched_at": "2026-03-12T14:05:30.233709+00:00"
  },
  {
    "id": "tag:google.com,2013:googlealerts/feed:11273504148675261032",
    "title": "電子五哥2月營收比一比！<b>緯創</b>年增177%再度超車廣達和碩仁寶承壓 - Yahoo股市",
    "link": "https://www.google.com/url?rct=j&sa=t&url=https://tw.stock.yahoo.com/news/%25E9%259B%25BB%25E5%25AD%2590%25E4%25BA%2594%25E5%2593%25A52%25E6%259C%2588%25E7%2587%259F%25E6%2594%25B6%25E6%25AF%2594%25E4%25B8%2580%25E6%25AF%2594%25EF%25BC%2581%25E7%25B7%25AF%25E5%2589%25B5%25E5%25B9%25B4%25E5%25A2%259E177%25E5%2586%258D%25E5%25BA%25A6%25E8%25B6%2585%25E8%25BB%258A%25E5%25BB%25A3%25E9%2581%2594-%25E5%2592%258C%25E7%25A2%25A9%25E4%25BB%2581%25E5%25AF%25B6%25E6%2589%25BF%25E5%25A3%2593-061936113.html&ct=ga&cd=CAIyHTI1ZGU5MDQ5NWZhNGM3ZGQ6Y29tOnpoLVRXOlRX&usg=AOvVaw3H9OYFTFK0zwZCrguGPX_P",
    "published": "2026-03-12T06:33:25Z",
    "summary": "... 更新時間 2026年3月11日週三下午11:32. <b>緯創</b>. <b>3231</b>.TW. 132.5(0.38%) &middot; 和碩. 4938.TW. 77.1(9.99%) &middot; 廣達. 2382.TW. 288.5(0.17%) &middot; 仁寶. 2324.TW. 32.65(&nbsp;...",
    "stock_id": "3231",
    "name": "緯創",
    "fetched_at": "2026-03-12T14:05:30.233714+00:00"
  },
  {
    "id": "tag:google.com,2013:googlealerts/feed:9704405674344540397",
    "title": "甲骨文狂上修展望！鴻海、廣達、<b>緯創</b>等台廠同步迎大單2027年度營收預測至900億美元",
    "link": "https://www.google.com/url?rct=j&sa=t&url=https://www.ftnn.com.tw/news/529278&ct=ga&cd=CAIyHTI1ZGU5MDQ5NWZhNGM3ZGQ6Y29tOnpoLVRXOlRX&usg=AOvVaw27mj6UbtNnEaJ-wAivDqTp",
    "published": "2026-03-12T04:53:34Z",
    "summary": "法人分析，隨著甲骨文持續擴大AI資料中心與算力投資，台灣AI伺服器供應鏈包括鴻海（2317）、廣達（2382）、<b>緯創</b>（<b>3231</b>）、緯穎（6669）與神達（3706）等廠商可望同步受惠。",
    "stock_id": "3231",
    "name": "緯創",
    "fetched_at": "2026-03-12T14:05:30.233717+00:00"
  },
  {
    "id": "tag:google.com,2013:googlealerts/feed:4666683102844187325",
    "title": "【即時新聞】最新公告！<b>緯創</b>去年淨利大增逾五成創歷史新高，擬配發5.5元現金股利 - 理財寶",
    "link": "https://www.google.com/url?rct=j&sa=t&url=https://www.cmoney.tw/forum/article/177394563&ct=ga&cd=CAIyHTI1ZGU5MDQ5NWZhNGM3ZGQ6Y29tOnpoLVRXOlRX&usg=AOvVaw2g2Uv5pYJuw1IU9m-con8a",
    "published": "2026-03-12T17:05:36Z",
    "summary": "代工大廠<b>緯創</b>(<b>3231</b>)今日最新公布去年財報結果，全年稅後淨利達兩百七十四億元，較前一年大幅成長百分之五十七，每股純益高達九點零四元，整體獲利表現創下歷史&nbsp;...",
    "stock_id": "3231",
    "name": "緯創",
    "fetched_at": "2026-03-12T17:52:10.649673+00:00"
  },
  {
    "id": "tag:google.com,2013:googlealerts/feed:12351704116644214024",
    "title": "<b>緯創</b>2025年EPS 9.04元將發5.5元| 集中市場| 證券 - 經濟日報",
    "link": "https://www.google.com/url?rct=j&sa=t&url=https://money.udn.com/money/story/5710/9376807&ct=ga&cd=CAIyHTI1ZGU5MDQ5NWZhNGM3ZGQ6Y29tOnpoLVRXOlRX&usg=AOvVaw0n_wicnW_bjI5rYWWRVRm1",
    "published": "2026-03-12T17:02:32Z",
    "summary": "<b>緯創</b>（<b>3231</b>）昨（12）日公布去年平均毛利率6.1％，年減約1.9個百分點；稅後純益274.08億元，創新高，年增57.1％，每股純益9.04元。",
    "stock_id": "3231",
    "name": "緯創",
    "fetched_at": "2026-03-12T17:52:10.649684+00:00"
  },
  {
    "id": "tag:google.com,2013:googlealerts/feed:10111781472641535863",
    "title": "<b>緯創</b>114年綜合損益表，每股盈餘9.04元| MoneyDJ理財網 - LINE TODAY",
    "link": "https://www.google.com/url?rct=j&sa=t&url=https://today.line.me/tw/v3/article/Ya8GBBp&ct=ga&cd=CAIyHTI1ZGU5MDQ5NWZhNGM3ZGQ6Y29tOnpoLVRXOlRX&usg=AOvVaw0s_KJU6MOT4uf0__aqGzJq",
    "published": "2026-03-12T15:34:06Z",
    "summary": "<b>緯創</b>(<b>3231</b>) 114年綜合損益表民國114年單位：新台幣仟元會計項目114年113年本期累計去年同期累計金額% 金額...",
    "stock_id": "3231",
    "name": "緯創",
    "fetched_at": "2026-03-12T17:52:10.649689+00:00"
  },
  {
    "id": "tag:google.com,2013:googlealerts/feed:12167190202710139347",
    "title": "〈<b>緯創</b>財報〉去年EPS 9.04元配息5.5元再斥資28億元擴大AI業務投資 - 鉅亨網",
    "link": "https://www.google.com/url?rct=j&sa=t&url=https://news.cnyes.com/news/id/6381798&ct=ga&cd=CAIyHTI1ZGU5MDQ5NWZhNGM3ZGQ6Y29tOnpoLVRXOlRX&usg=AOvVaw36Oh8mTd4KP5RXwkKJewHF",
    "published": "2026-03-12T15:24:05Z",
    "summary": "<b>緯創</b>(<b>3231</b>-TW) 今(12) 日公告最新財報，2025 年稅後純益274.08 億元，年增超過5 成，每股純益9.04 元。另外，為因應AI 相關業務擴增，董事會通過新竹廠區及墨西哥&nbsp;...",
    "stock_id": "3231",
    "name": "緯創",
    "fetched_at": "2026-03-12T17:52:10.649693+00:00"
  },
  {
    "id": "tag:google.com,2013:googlealerts/feed:12950996480320646504",
    "title": "<b>緯創</b>股利：現金5.5元 - Yahoo股市",
    "link": "https://www.google.com/url?rct=j&sa=t&url=https://tw.stock.yahoo.com/news/%25E7%25B7%25AF%25E5%2589%25B5%25E8%2582%25A1%25E5%2588%25A9-%25E7%258F%25BE%25E9%2587%25915-5%25E5%2585%2583-134000080.html&ct=ga&cd=CAIyHTI1ZGU5MDQ5NWZhNGM3ZGQ6Y29tOnpoLVRXOlRX&usg=AOvVaw2oaXL2Y9uXS66NqVB0TRCK",
    "published": "2026-03-12T15:19:27Z",
    "summary": "公開資訊觀測站重大訊息公告(<b>3231</b>)<b>緯創</b>-董事會決議股利分派1. 董事會擬議日期：115/03/122. 股利所屬年(季)度：114年年度3. 股利所屬期間：114/01/01&nbsp;...",
    "stock_id": "3231",
    "name": "緯創",
    "fetched_at": "2026-03-12T17:52:10.649697+00:00"
  },
  {
    "id": "tag:google.com,2013:googlealerts/feed:1371653773621658033",
    "title": "【即時新聞】最新宣布！<b>緯創</b>2025年財報營收達2.19兆翻倍成長，獲利創歷史新高",
    "link": "https://www.google.com/url?rct=j&sa=t&url=https://www.cmoney.tw/forum/article/177393897&ct=ga&cd=CAIyHTI1ZGU5MDQ5NWZhNGM3ZGQ6Y29tOnpoLVRXOlRX&usg=AOvVaw2XvCSfwTQ6KsHNjgyRWks_",
    "published": "2026-03-12T14:59:33Z",
    "summary": "<b>緯創</b>. <b>3231</b>. 133. 4 (+3.10%). 最新時事. 6 天前 投資網誌. 【即時新聞】<b>緯創</b>2月營收狂飆2848億創新高，AI伺服器帶動年增177% &middot; 03月04日 投資網誌. 【美股焦點】&nbsp;...",
    "stock_id": "3231",
    "name": "緯創",
    "fetched_at": "2026-03-12T17:52:10.649701+00:00"
  },
  {
    "id": "tag:google.com,2013:googlealerts/feed:17765142633733138714",
    "title": "〈<b>緯創</b>財報〉去年EPS 9.04元配息5.5元再斥資28億元擴大AI業務投資 - LINE TODAY",
    "link": "https://www.google.com/url?rct=j&sa=t&url=https://today.line.me/tw/v3/article/Opq56OB%3Fview%3Dtopic%26referral%3DAI&ct=ga&cd=CAIyHTI1ZGU5MDQ5NWZhNGM3ZGQ6Y29tOnpoLVRXOlRX&usg=AOvVaw0bhBSfplk0o4C5B93N6DgF",
    "published": "2026-03-12T14:54:26Z",
    "summary": "<b>緯創</b>(<b>3231</b>-TW) 今(12) 日公告最新財報，2025 年稅後純益274.08 億元，年增超過5 成，每股純益9.04 元。...",
    "stock_id": "3231",
    "name": "緯創",
    "fetched_at": "2026-03-12T17:52:10.649705+00:00"
  },
  {
    "id": "tag:google.com,2013:googlealerts/feed:15835423212860651399",
    "title": "<b>緯創</b>將發現金股利5.5元！砸10.46億擴AI產能 - Yahoo奇摩新聞",
    "link": "https://www.google.com/url?rct=j&sa=t&url=https://tw.news.yahoo.com/%25E7%25B7%25AF%25E5%2589%25B5%25E5%25B0%2587%25E7%2599%25BC%25E7%258F%25BE%25E9%2587%2591%25E8%2582%25A1%25E5%2588%25A95-5%25E5%2585%2583-%25E7%25A0%25B810-46%25E5%2584%2584%25E6%2593%25B4ai%25E7%2594%25A2%25E8%2583%25BD-103327998.html&ct=ga&cd=CAIyHTI1ZGU5MDQ5NWZhNGM3ZGQ6Y29tOnpoLVRXOlRX&usg=AOvVaw2W5_w9nt_T9gJkM31SK8Ox",
    "published": "2026-03-12T14:43:27Z",
    "summary": "<b>緯創</b>. <b>3231</b>.TW. 132.5(0.38%). △<b>緯創</b>今日召開董事會，決議每股將配發現金股利5.5元。（圖／取自<b>緯創</b>Youtube頻道）.",
    "stock_id": "3231",
    "name": "緯創",
    "fetched_at": "2026-03-12T17:52:10.649709+00:00"
  },
  {
    "id": "tag:google.com,2013:googlealerts/feed:16965237273793427130",
    "title": "<b>緯創</b>去年賺274億元！每股配息5.5元殖利率逾4% | 中天新聞網 - LINE TODAY",
    "link": "https://www.google.com/url?rct=j&sa=t&url=https://today.line.me/hk/v3/article/zN25JP6&ct=ga&cd=CAIyHTI1ZGU5MDQ5NWZhNGM3ZGQ6Y29tOnpoLVRXOlRX&usg=AOvVaw3cIxQ8-zheNeorKdmOs9dr",
    "published": "2026-03-12T14:35:37Z",
    "summary": "<b>緯創</b>（<b>3231</b>）於今（12）日傍晚5點51分發布重大訊息，公告董事會通過114年度財務報告，全年稅後淨利達274.08億元，年增57.1％，...",
    "stock_id": "3231",
    "name": "緯創",
    "fetched_at": "2026-03-12T17:52:10.649713+00:00"
  },
  {
    "id": "tag:google.com,2013:googlealerts/feed:18365983850347027755",
    "title": "<b>緯創</b>去年每股賺9.04元創新高加碼投資新竹與墨西哥廠 - Yahoo股市",
    "link": "https://www.google.com/url?rct=j&sa=t&url=https://tw.stock.yahoo.com/news/%25E7%25B7%25AF%25E5%2589%25B5%25E5%258E%25BB%25E5%25B9%25B4%25E6%25AF%258F%25E8%2582%25A1%25E8%25B3%25BA9-04%25E5%2585%2583%25E5%2589%25B5%25E6%2596%25B0%25E9%25AB%2598-%25E5%258A%25A0%25E7%25A2%25BC%25E6%258A%2595%25E8%25B3%2587%25E6%2596%25B0%25E7%25AB%25B9%25E8%2588%2587%25E5%25A2%25A8%25E8%25A5%25BF%25E5%2593%25A5%25E5%25BB%25A0-140846667.html&ct=ga&cd=CAIyHTI1ZGU5MDQ5NWZhNGM3ZGQ6Y29tOnpoLVRXOlRX&usg=AOvVaw2xDyADbLHaalk0RSF3r5pe",
    "published": "2026-03-12T14:28:31Z",
    "summary": "中央社記者吳家豪台北2026年03月12日電）代工廠<b>緯創</b>(<b>3231</b>)今天公布2025年度財報，合併營收約新台幣2.187兆元，年增1.08倍，歸屬母公司淨利274.08億元，年增57.1%，&nbsp;...",
    "stock_id": "3231",
    "name": "緯創",
    "fetched_at": "2026-03-12T17:52:10.649717+00:00"
  },
  {
    "id": "tag:google.com,2013:googlealerts/feed:279354938033745240",
    "title": "<b>緯創</b>114年綜合損益表，每股盈餘9.04元- 新聞- MoneyDJ理財網",
    "link": "https://www.google.com/url?rct=j&sa=t&url=https://www.moneydj.com/KMDJ/News/NewsViewer.aspx%3Fa%3D4af4e8a6-f0d4-4dd7-85bc-69db88a4225d&ct=ga&cd=CAIyHTI1ZGU5MDQ5NWZhNGM3ZGQ6Y29tOnpoLVRXOlRX&usg=AOvVaw2KZbe2Y6W54p3LUuycvvP7",
    "published": "2026-03-12T14:20:25Z",
    "summary": "緯創114年綜合損益表，每股盈餘9.04元. 2026/03/12 21:43. <b>緯創</b>(<b>3231</b>) 114年 綜合損益表. 民國114年. 單位：新台幣仟元. 會計項目, 114年, 113年, 本期累計, 去年&nbsp;...",
    "stock_id": "3231",
    "name": "緯創",
    "fetched_at": "2026-03-12T17:52:10.649721+00:00"
  },
  {
    "id": "tag:google.com,2013:googlealerts/feed:12961884681244735836",
    "title": "<b>緯創</b>114年綜合損益表，每股盈餘9.04元- 新聞- MoneyDJ理財網",
    "link": "https://www.google.com/url?rct=j&sa=t&url=https://www.moneydj.com/kmdj/news/newsviewer.aspx%3Fa%3D4af4e8a6-f0d4-4dd7-85bc-69db88a4225d&ct=ga&cd=CAIyHTI1ZGU5MDQ5NWZhNGM3ZGQ6Y29tOnpoLVRXOlRX&usg=AOvVaw0_qQd4oQA5izhjpHdxl9LB",
    "published": "2026-03-12T14:20:01Z",
    "summary": "緯創114年綜合損益表，每股盈餘9.04元. 2026/03/12 21:43. <b>緯創</b>(<b>3231</b>) 114年 綜合損益表. 民國114年. 單位：新台幣仟元. 會計項目, 114年, 113年, 本期累計, 去年&nbsp;...",
    "stock_id": "3231",
    "name": "緯創",
    "fetched_at": "2026-03-12T17:52:10.649725+00:00"
  },
  {
    "id": "tag:google.com,2013:googlealerts/feed:14106732479627962162",
    "title": "<b>緯創</b>財報／營收、獲利皆創歷史新高將持續擴充產能 - CMoney 理財寶",
    "link": "https://www.google.com/url?rct=j&sa=t&url=https://www.cmoney.tw/forum/article/177391864&ct=ga&cd=CAIyHTI1ZGU5MDQ5NWZhNGM3ZGQ6Y29tOnpoLVRXOlRX&usg=AOvVaw3pJZVJN7xKEtTq4gXJpo4c",
    "published": "2026-03-12T14:03:38Z",
    "summary": "<b>緯創</b>（<b>3231</b>）於12日公告去年財報，2025年合併營收達2.19兆元，較前年同期翻倍成長，並創下歷史新高；歸屬於母公司業主淨利274.1億元，年增57%；每股.",
    "stock_id": "3231",
    "name": "緯創",
    "fetched_at": "2026-03-12T17:52:10.649728+00:00"
  },
  {
    "id": "tag:google.com,2013:googlealerts/feed:15221516984829132232",
    "title": "<b>緯創</b>去年賺274億元！每股配息5.5元殖利率逾4% - 中天新聞網",
    "link": "https://www.google.com/url?rct=j&sa=t&url=https://ctinews.com/news/items/rPnv4rXXaY&ct=ga&cd=CAIyHTI1ZGU5MDQ5NWZhNGM3ZGQ6Y29tOnpoLVRXOlRX&usg=AOvVaw3Cm_gFT-5nNiiHHmDM9iCN",
    "published": "2026-03-12T13:37:42Z",
    "summary": "<b>緯創</b>（<b>3231</b>）於今（12）日傍晚5點51分發布重大訊息，公告董事會通過114年度財務報告，全年稅後淨利達274.08億元，年增57.1％，每股純益9.04元創歷史新高。",
    "stock_id": "3231",
    "name": "緯創",
    "fetched_at": "2026-03-12T17:52:10.649732+00:00"
  },
  {
    "id": "tag:google.com,2013:googlealerts/feed:14032184796041846900",
    "title": "【即時新聞】最新宣布！<b>緯創</b>2025年財報營收達2.19兆翻倍成長，獲利創歷史新高",
    "link": "https://www.google.com/url?rct=j&sa=t&url=https://www.cmoney.tw/notes/note-detail.aspx%3Fnid%3D1145717&ct=ga&cd=CAIyHTI1ZGU5MDQ5NWZhNGM3ZGQ6Y29tOnpoLVRXOlRX&usg=AOvVaw1g6QUsBzAUKz5z4FAcQxOG",
    "published": "2026-03-12T13:37:00Z",
    "summary": "權知道 &middot; AI伺服器需求強勁帶動產能擴充計畫 &middot; 高配息政策與籌資備戰引發市場關注 &middot; 股東會登場與後續產能開出進度成焦點 &middot; <b>緯創</b>(<b>3231</b>)：近期基本面、籌碼面與技術面&nbsp;...",
    "stock_id": "3231",
    "name": "緯創",
    "fetched_at": "2026-03-12T17:52:10.649736+00:00"
  },
  {
    "id": "tag:google.com,2013:googlealerts/feed:12848791254958699859",
    "title": "目標價上看370元！大摩點名「伺服器機櫃大廠」出貨狂飆<b>緯創</b>、鴻海等吃大單...輝達GB200",
    "link": "https://www.google.com/url?rct=j&sa=t&url=https://www.ftnn.com.tw/news/529282&ct=ga&cd=CAIyHTI1ZGU5MDQ5NWZhNGM3ZGQ6Y29tOnpoLVRXOlRX&usg=AOvVaw1F6eTD5jtfhvdqA98ngmUq",
    "published": "2026-03-12T13:08:24Z",
    "summary": "法人預期，在AI資料中心需求持續擴張下，今年全年出貨量有機會衝上7萬至8萬台，較2025年約2.9萬台規模幾乎倍增，台灣系統代工廠<b>緯創</b>（<b>3231</b>）、鴻海（2317&nbsp;...",
    "stock_id": "3231",
    "name": "緯創",
    "fetched_at": "2026-03-12T17:52:10.649740+00:00"
  },
  {
    "id": "tag:google.com,2013:googlealerts/feed:4911857209924134283",
    "title": "<b>緯創</b>宣布配息5.5元重金加碼台美AI產能 - BTCC",
    "link": "https://www.google.com/url?rct=j&sa=t&url=https://www.btcc.com/zh-TW/square/ltnTW/1579859&ct=ga&cd=CAIyHTI1ZGU5MDQ5NWZhNGM3ZGQ6Y29tOnpoLVRXOlRX&usg=AOvVaw0o-a3ukY2bWHmqga7hYulQ",
    "published": "2026-03-12T12:53:11Z",
    "summary": "創近年積極強化AI相關產品布局，並同步推動全球產能升級與供應鏈調整。（資料照） 〔記者方韋傑／台北報導〕<b>緯創</b>（<b>3231</b>）去年每股盈餘（EPS）9.04元，管理層今日通過&nbsp;...",
    "stock_id": "3231",
    "name": "緯創",
    "fetched_at": "2026-03-12T17:52:10.649743+00:00"
  },
  {
    "id": "tag:google.com,2013:googlealerts/feed:10231743391634091905",
    "title": "【即時新聞】最新公告！<b>緯創</b>去年淨利大增逾五成創歷史新高，擬配發5.5元現金股利",
    "link": "https://www.google.com/url?rct=j&sa=t&url=https://cmnews.com.tw/article/newsyoudeservetoknow-4b93e088-1e11-11f1-a4b3-f1a479d5597a&ct=ga&cd=CAIyHTI1ZGU5MDQ5NWZhNGM3ZGQ6Y29tOnpoLVRXOlRX&usg=AOvVaw0vmrGPZ5Z7-DhoRzE9tAWx",
    "published": "2026-03-12T12:48:11Z",
    "summary": "<b>緯創</b>(<b>3231</b>)最新公布去年財報淨利創歷史新高，擬配發5.5元現金股利。本文解析緯創營收表現、擴產布局，並結合近期籌碼與技術面數據，提供資深投資人關鍵決策參考&nbsp;...",
    "stock_id": "3231",
    "name": "緯創",
    "fetched_at": "2026-03-12T17:52:10.649747+00:00"
  },
  {
    "id": "tag:google.com,2013:googlealerts/feed:12024213844373928739",
    "title": "【即時新聞】最新宣布！<b>緯創</b>2025年財報營收達2.19兆翻倍成長，獲利創歷史新高",
    "link": "https://www.google.com/url?rct=j&sa=t&url=https://cmnews.com.tw/article/newsyoudeservetoknow-08eb6b42-1e11-11f1-bf17-51b367525a68&ct=ga&cd=CAIyHTI1ZGU5MDQ5NWZhNGM3ZGQ6Y29tOnpoLVRXOlRX&usg=AOvVaw0gtN5WUdYaJN3hgSH_A_qy",
    "published": "2026-03-12T12:44:53Z",
    "summary": "<b>緯創</b>(<b>3231</b>)：近期基本面、籌碼面與技術面表現. 基本面亮點. 緯創身為全球前三大NB代工廠，近年積極轉型並受惠於AI伺服器需求，今年2月合併營收高達2,848.9億元&nbsp;...",
    "stock_id": "3231",
    "name": "緯創",
    "fetched_at": "2026-03-12T17:52:10.649751+00:00"
  },
  {
    "id": "tag:google.com,2013:googlealerts/feed:6592576080111795141",
    "title": "<b>緯創</b>財報／去年獲利創新高每股將配5.5元現金股利 - 經濟日報",
    "link": "https://www.google.com/url?rct=j&sa=t&url=https://money.udn.com/money/story/5710/9376664&ct=ga&cd=CAIyHTI1ZGU5MDQ5NWZhNGM3ZGQ6Y29tOnpoLVRXOlRX&usg=AOvVaw03SW0YITnoR1FkFxM8WT_B",
    "published": "2026-03-12T12:29:36Z",
    "summary": "代工大廠<b>緯創</b>（<b>3231</b>）公告2025年財報，去年稅後淨利274.08億元，不僅相較2024年明顯增加57.1％，且獲利表現更將近賺一個股本，每股純益9.04元。緯創預計每股將配&nbsp;...",
    "stock_id": "3231",
    "name": "緯創",
    "fetched_at": "2026-03-12T17:52:10.649755+00:00"
  }
]