[
  {
    "id": "tag:google.com,2013:googlealerts/feed:8373701809982511797",
    "title": "《外資》賣超股：台積電、華航、華碩(2-1) - 旺得富理財網",
    "link": "https://www.google.com/url?rct=j&sa=t&url=https://wantrich.chinatimes.com/news/20260305900076-420101&ct=ga&cd=CAIyHTI4MGEwZjgwMTQ3NzVkMWY6Y29tOnpoLVRXOlRX&usg=AOvVaw3cKmzBzaDZ-vNjmL6uUePY",
    "published": "2026-03-04T23:54:56Z",
    "summary": "神達(3706) 威盛(2388) <b>技嘉</b>(<b>2376</b>) 成霖(9934) 百和(9938) &middot; 三芳(1307) 新興(2605) 和大(1536) 勤美(1532) 友訊(2332). 皇普(2528) 南港(2101) 冠德(2520) 茂&nbsp;...",
    "stock_id": "2376",
    "name": "技嘉",
    "fetched_at": "2026-03-06T03:28:33.926241+00:00"
  },
  {
    "id": "tag:google.com,2013:googlealerts/feed:9637021900902890420",
    "title": "高盛：<b>技嘉</b>評等中立 - CMoney 理財寶",
    "link": "https://www.google.com/url?rct=j&sa=t&url=https://www.cmoney.tw/forum/article/177180154&ct=ga&cd=CAIyHTI4MGEwZjgwMTQ3NzVkMWY6Y29tOnpoLVRXOlRX&usg=AOvVaw3Iy45xZyaJJWkK21T18LHp",
    "published": "2026-03-04T23:10:55Z",
    "summary": "心得：<b>技嘉</b>只能中立啊？這樣的表現是想讓人哭出來嗎？---根據高盛證券的報告，台灣的AI供應鏈成長列車正在加速，<b>技嘉</b>（<b>2376</b>）被列入供應鏈的成員之一。2月由於適.",
    "stock_id": "2376",
    "name": "技嘉",
    "fetched_at": "2026-03-06T03:28:33.926252+00:00"
  }
]