[
  {
    "id": "tag:google.com,2013:googlealerts/feed:2725069835156969335",
    "title": "法人提款大盤轉布局15檔遺珠- 日報- 工商時報",
    "link": "https://www.google.com/url?rct=j&sa=t&url=https://www.ctee.com.tw/news/20260330700171-439901&ct=ga&cd=CAIyHTUzZjYxZGE4MDRiOTAxMjE6Y29tOnpoLVRXOlRX&usg=AOvVaw39C7MDwjOxnzgvz0K7ngs7",
    "published": "2026-03-29T19:10:45Z",
    "summary": "... <b>啟碁</b>（<b>6285</b>）、中租-KY（5871）及聯詠（3034）等，各加碼11億～ ... 台股. 外資27日買超逾10億元有<b>啟碁</b>（<b>6285</b>&nbsp;...",
    "stock_id": "6285",
    "name": "啟碁",
    "fetched_at": "2026-03-29T19:36:51.627584+00:00"
  },
  {
    "id": "tag:google.com,2013:googlealerts/feed:3401045591163648540",
    "title": "<b>啟碁</b>訂單能見度旺- 日報- 工商時報",
    "link": "https://www.google.com/url?rct=j&sa=t&url=https://www.ctee.com.tw/news/20260330700223-439901&ct=ga&cd=CAIyHTUzZjYxZGE4MDRiOTAxMjE6Y29tOnpoLVRXOlRX&usg=AOvVaw2U0nk8UwWnIjQ_VmU2SyLO",
    "published": "2026-03-29T19:10:42Z",
    "summary": "<b>啟碁</b>相關權證網通大廠啓碁（<b>6285</b>）搶搭低軌衛星及AI伺服器列車有成，2026年隨著網路交換器（高階Core Switch）進入800G Switch產業上升循環，啓碁來自AI Server用&nbsp;...",
    "stock_id": "6285",
    "name": "啟碁",
    "fetched_at": "2026-03-29T19:36:51.627597+00:00"
  },
  {
    "id": "tag:google.com,2013:googlealerts/feed:1107289585942557285",
    "title": "<b>6285 啟碁</b>- 這操作真的… - 股市爆料同學會",
    "link": "https://www.google.com/url?rct=j&sa=t&url=https://www.cmoney.tw/forum/article/177746336&ct=ga&cd=CAIyHTUzZjYxZGE4MDRiOTAxMjE6Y29tOnpoLVRXOlRX&usg=AOvVaw2rtttm55ZaFkRzb4W4M0JU",
    "published": "2026-03-29T12:11:34Z",
    "summary": "** <b>6285啟碁</b>. ** 6683雍智科技（2月營收新高，IC測試板、老化測試板與探針卡 ... 【10:20 即時新聞】<b>啟碁</b>(<b>6285</b>)股價走強漲逾4%，低軌衛星題材發酵帶動買&nbsp;...",
    "stock_id": "6285",
    "name": "啟碁",
    "fetched_at": "2026-03-29T19:36:51.627602+00:00"
  },
  {
    "id": "tag:google.com,2013:googlealerts/feed:16602684178249560807",
    "title": "<b>6285 啟碁</b>- 低軌衛星少數本益比還很低的加油點啦- 股市爆料同學會 - 理財寶",
    "link": "https://www.google.com/url?rct=j&sa=t&url=https://www.cmoney.tw/forum/article/177718295&ct=ga&cd=CAIyHTUzZjYxZGE4MDRiOTAxMjE6Y29tOnpoLVRXOlRX&usg=AOvVaw2Fgqi0EZskbHACJeRsSYSt",
    "published": "2026-03-29T11:38:29Z",
    "summary": "2,392 &middot; <b>啟碁</b>. <b>6285</b>. 172. 8 (-4.44%). 最新時事. 3 天前 投資網誌. 【最新消息】傳SpaceX將申請上市，「8檔概念股」強勢上攻！ 3 天前 投資網誌. 【13:17 即時&nbsp;...",
    "stock_id": "6285",
    "name": "啟碁",
    "fetched_at": "2026-03-29T19:36:51.627607+00:00"
  },
  {
    "id": "tag:google.com,2013:googlealerts/feed:3261736284275061797",
    "title": "<b>6285 啟碁</b>- Gg - 股市爆料同學會 - 理財寶",
    "link": "https://www.google.com/url?rct=j&sa=t&url=https://www.cmoney.tw/forum/article/177741770&ct=ga&cd=CAIyHTUzZjYxZGE4MDRiOTAxMjE6Y29tOnpoLVRXOlRX&usg=AOvVaw1IFoZ8nc_kJ3eIRpSK9-1h",
    "published": "2026-03-29T10:10:20Z",
    "summary": "<b>啟碁</b>. <b>6285</b>. -. -. (-) &middot; 華通. 2313. -. -. (-).",
    "stock_id": "6285",
    "name": "啟碁",
    "fetched_at": "2026-03-29T19:36:51.627611+00:00"
  },
  {
    "id": "tag:google.com,2013:googlealerts/feed:14976767974573679315",
    "title": "<b>6285 啟碁</b>- 再來一波好不好- 股市爆料同學會 - 理財寶",
    "link": "https://www.google.com/url?rct=j&sa=t&url=https://www.cmoney.tw/forum/article/177746395&ct=ga&cd=CAIyHTUzZjYxZGE4MDRiOTAxMjE6Y29tOnpoLVRXOlRX&usg=AOvVaw35Cp6ZCfdWE0HMemuX8MlS",
    "published": "2026-03-29T03:13:50Z",
    "summary": "<b>啟碁</b>. <b>6285</b>. 172. 8 (-4.44%). 最新時事. 3 天前 投資網誌. 【最新消息】傳SpaceX將申請上市，「8檔概念股」強勢上攻！ 3 天前 投資網誌. 【13:17 即時新聞】<b>啟碁</b>(&nbsp;...",
    "stock_id": "6285",
    "name": "啟碁",
    "fetched_at": "2026-03-29T19:36:51.627615+00:00"
  },
  {
    "id": "tag:google.com,2013:googlealerts/feed:16217396687517016041",
    "title": "<b>啟碁</b>(<b>6285</b>)200元目標價評估：客戶與產品集中度風險的關鍵影響解析 - 延伸閱讀文章",
    "link": "https://www.google.com/url?rct=j&sa=t&url=https://readmo.cmoney.tw/article/e835ad59-e0d1-47cf-90d4-aa0441977aaf&ct=ga&cd=CAIyHTUzZjYxZGE4MDRiOTAxMjE6Y29tOnpoLVRXOlRX&usg=AOvVaw37dxJaDmwTt5Je8AjYzmkK",
    "published": "2026-03-28T23:13:16Z",
    "summary": "展望2022 年，因Wi-Fi 6、5G 滲透率可望再提升，且2021 年無法出貨的訂單將遞延到2022 年。 市場維持<b>啟碁</b>(<b>6285</b>) 2021 年預估EPS 為4.02 元(YoY +6.9%)，並預估2022&nbsp;...",
    "stock_id": "6285",
    "name": "啟碁",
    "fetched_at": "2026-03-29T19:36:51.627619+00:00"
  },
  {
    "id": "tag:google.com,2013:googlealerts/feed:9175935640703941238",
    "title": "外資抄底記憶體！華邦電出手狂敲2.4萬張霸榜這檔也掃貨近萬張 - 理財寶",
    "link": "https://www.google.com/url?rct=j&sa=t&url=https://www.cmoney.tw/forum/article/177756810&ct=ga&cd=CAIyHTUzZjYxZGE4MDRiOTAxMjE6Y29tOnpoLVRXOlRX&usg=AOvVaw0Kv1wuCSFlmsgR2i5IK9tD",
    "published": "2026-03-28T23:09:14Z",
    "summary": "外資週五買超前10大個股，依序為華邦電（2344）2萬4119張、仁寶（2324）2萬2460張、<b>啟碁</b>（<b>6285</b>）1萬707張、中租-KY（5871）1萬506張、華通... 查看全文. 0.",
    "stock_id": "6285",
    "name": "啟碁",
    "fetched_at": "2026-03-29T19:36:51.627623+00:00"
  },
  {
    "id": "tag:google.com,2013:googlealerts/feed:17678568685652138437",
    "title": "《台北股市》外資27日買超股：華邦電、仁寶、<b>啟碁</b>",
    "link": "https://www.google.com/url?rct=j&sa=t&url=https://tw.stock.yahoo.com/news/%25E5%258F%25B0%25E5%258C%2597%25E8%2582%25A1%25E5%25B8%2582-%25E5%25A4%2596%25E8%25B3%258727%25E6%2597%25A5%25E8%25B2%25B7%25E8%25B6%2585%25E8%2582%25A1-%25E8%258F%25AF%25E9%2582%25A6%25E9%259B%25BB-%25E4%25BB%2581%25E5%25AF%25B6-%25E5%2595%259F%25E7%25A2%2581-015807559.html&ct=ga&cd=CAIyHTUzZjYxZGE4MDRiOTAxMjE6Y29tOnpoLVRXOlRX&usg=AOvVaw1Nj4FVXBv0XEdQ9a6ucGUQ",
    "published": "2026-03-28T21:54:48Z",
    "summary": "... <b>啟碁</b>(<b>6285</b>)名列二、三名，分別買超2萬2460張及買超1萬707張。第四及第五名為中租-KY(5871)、華通(2313)，其他依序為旺宏(2337)、燿華(2367)、長榮航(2618)&nbsp;...",
    "stock_id": "6285",
    "name": "啟碁",
    "fetched_at": "2026-03-29T19:36:51.627628+00:00"
  },
  {
    "id": "tag:google.com,2013:googlealerts/feed:9366250480160966523",
    "title": "太空經濟Big Bang！6G低軌衛星引爆「通訊革命」：昇達科、<b>啟碁</b> - 鉅亨網",
    "link": "https://www.google.com/url?rct=j&sa=t&url=https://news.cnyes.com/news/print/6398137%3Fexp%3Da&ct=ga&cd=CAIyHTUzZjYxZGE4MDRiOTAxMjE6Y29tOnpoLVRXOlRX&usg=AOvVaw2V8iGJVlVLeXnRCelP5cqm",
    "published": "2026-03-28T20:15:13Z",
    "summary": "... <b>啟碁</b>、科建. 鉅亨研報 ... 昇達科(3491-TW) 在波導管市場具備領導地位，受惠於衛星規格升級，其高毛利業務佔比將從2025 年的59% 躍升至2027 年的81%；<b>啟碁</b>(<b>6285</b>&nbsp;...",
    "stock_id": "6285",
    "name": "啟碁",
    "fetched_at": "2026-03-29T19:36:51.627632+00:00"
  },
  {
    "id": "tag:google.com,2013:googlealerts/feed:17313878233616297777",
    "title": "討論牆| 盤中速報- <b>啟碁</b>(<b>6285</b>)股價拉至漲停，漲停價189.0元，成交28,759張| LINE TODAY",
    "link": "https://www.google.com/url?rct=j&sa=t&url=https://today.line.me/tw/v3/posts/list/article/QwYOYGl&ct=ga&cd=CAIyHTUzZjYxZGE4MDRiOTAxMjE6Y29tOnpoLVRXOlRX&usg=AOvVaw0zdsZcXpXDShbT5NSqFMmd",
    "published": "2026-03-28T18:47:54Z",
    "summary": "0則貼文| 快來參與LINE TODAY討論牆上的討論| 盤中速報- <b>啟碁</b>(<b>6285</b>)股價拉至漲停，漲停價189.0元，成交28,75...",
    "stock_id": "6285",
    "name": "啟碁",
    "fetched_at": "2026-03-29T19:36:51.627636+00:00"
  },
  {
    "id": "tag:google.com,2013:googlealerts/feed:14427345473986539134",
    "title": "<b>啟碁</b>- MACD ，KD ，KDJ 都往上囉~當然續噴- 股市爆料同學會 - 理財寶",
    "link": "https://www.google.com/url?rct=j&sa=t&url=https://www.cmoney.tw/forum/article/177771514&ct=ga&cd=CAIyHTUzZjYxZGE4MDRiOTAxMjE6Y29tOnpoLVRXOlRX&usg=AOvVaw09MZXr4sT117n83c-OJd5G",
    "published": "2026-03-28T18:27:37Z",
    "summary": "【12:18 即時新聞】<b>啟碁</b>(<b>6285</b>)股價上漲逾4%至173.5元，太空衛星＋5G網通題材點火，短線挑戰壓力區技術與籌碼修復成關鍵 &middot; 4 天前 投資網誌.",
    "stock_id": "6285",
    "name": "啟碁",
    "fetched_at": "2026-03-29T19:36:51.627639+00:00"
  },
  {
    "id": "tag:google.com,2013:googlealerts/feed:4213080092833284731",
    "title": "盤中速報- <b>啟碁</b>(<b>6285</b>)股價拉至漲停，漲停價189.0元",
    "link": "https://www.google.com/url?rct=j&sa=t&url=https://fpsantamaria.es/bahia/noticias/&ct=ga&cd=CAIyHTUzZjYxZGE4MDRiOTAxMjE6Y29tOnpoLVRXOlRX&usg=AOvVaw1sbPB3F1YbDX5su3bffahV",
    "published": "2026-03-28T08:56:38Z",
    "summary": "<b>啟碁</b>(<b>6285</b>-TW)27日11:29上漲17元，股價漲停報189.0元，委買5張、委賣5,236張，成交28,759張。 主要業務為衛星通訊系列產品。移動與攜帶產品之通訊系列產品。",
    "stock_id": "6285",
    "name": "啟碁",
    "fetched_at": "2026-03-29T19:36:51.627644+00:00"
  },
  {
    "id": "tag:google.com,2013:googlealerts/feed:15563811941986873932",
    "title": "低軌衛星Q2噴發！不是昇達科法人點名SpaceX供應商首選是它：明年獲利增6成",
    "link": "https://www.google.com/url?rct=j&sa=t&url=https://wantrich.chinatimes.com/news/20260330900002-420101&ct=ga&cd=CAIyHTUzZjYxZGE4MDRiOTAxMjE6Y29tOnpoLVRXOlRX&usg=AOvVaw0b6Ere0mllxfrTYwbRy3Lr",
    "published": "2026-03-29T22:40:36Z",
    "summary": "... <b>啟碁</b>(<b>6285</b>)。 受惠營運商大規模部署與地面終端設備需求同步提升，法人看好2026年第2季衛星零組件備貨動能。由於SpaceX仍是多數台廠最大客戶，在台鏈當中以華&nbsp;...",
    "stock_id": "6285",
    "name": "啟碁",
    "fetched_at": "2026-03-29T23:39:18.223254+00:00"
  },
  {
    "id": "tag:google.com,2013:googlealerts/feed:12658483255603254168",
    "title": "法人提款大盤轉布局15檔遺珠- 證券．權證- 工商時報",
    "link": "https://www.google.com/url?rct=j&sa=t&url=https://www.chinatimes.com/newspapers/20260330000299-260206&ct=ga&cd=CAIyHTUzZjYxZGE4MDRiOTAxMjE6Y29tOnpoLVRXOlRX&usg=AOvVaw0PAxuP9_pOF8g1Mc-gYdw-",
    "published": "2026-03-29T20:17:34Z",
    "summary": "... 外資27日買超逾10億元有<b>啟碁</b>（<b>6285</b>）、中租-KY（5871）及聯詠（3034）等，各加碼11億～29億元以上。圖／本報資料照片. Facebook; Line; Threads&nbsp;...",
    "stock_id": "6285",
    "name": "啟碁",
    "fetched_at": "2026-03-29T23:39:18.223265+00:00"
  },
  {
    "id": "tag:google.com,2013:googlealerts/feed:16333080468296472502",
    "title": "台股太空經濟6G低軌衛星引爆「通訊革命」：昇達科、<b>啟碁</b>、科建",
    "link": "https://www.google.com/url?rct=j&sa=t&url=https://www.cmoney.tw/forum/article/177773687&ct=ga&cd=CAIyHTUzZjYxZGE4MDRiOTAxMjE6Y29tOnpoLVRXOlRX&usg=AOvVaw2exeG9mBtP7vVLcU8Kcpfl",
    "published": "2026-03-29T17:10:49Z",
    "summary": "昇達科. 文章. Scroll left. 昇達科. 3491. 1665. 115. (+7.42%) &middot; <b>啟碁</b>. <b>6285</b>. 188.5. 16.5. (+9.59%) &middot; 科建. 7886. 200. 11.47. (-5.42%). Scroll right.",
    "stock_id": "6285",
    "name": "啟碁",
    "fetched_at": "2026-03-29T23:39:18.223279+00:00"
  },
  {
    "id": "tag:google.com,2013:googlealerts/feed:8495140515167953643",
    "title": "盤中速報- 雍智科技(6683)大漲7.22%，報1485元| 鉅亨網",
    "link": "https://www.google.com/url?rct=j&sa=t&url=https://news.cnyes.com/news/id/6401111&ct=ga&cd=CAIyHTUzZjYxZGE4MDRiOTAxMjE6Y29tOnpoLVRXOlRX&usg=AOvVaw3esgBuqcAkMN-Gk1Aesnyv",
    "published": "2026-03-30T03:54:07Z",
    "summary": "盤中速報- <b>啟碁</b>(<b>6285</b>)大跌7.16%，報175元. tab-icon. 其他 ... <b>啟碁</b>. -3.18% &middot; 中租-KY. -1.33% &middot; 復華彭博新興債. %台股台股盤後表格. 08:48&nbsp;...",
    "stock_id": "6285",
    "name": "啟碁",
    "fetched_at": "2026-03-30T05:30:48.343838+00:00"
  },
  {
    "id": "tag:google.com,2013:googlealerts/feed:10824811957866397294",
    "title": "【即時新聞】<b>啟碁</b>(<b>6285</b>)外資狂掃20億卻重挫，這「5檔概念股」多空激戰大洗盤！",
    "link": "https://www.google.com/url?rct=j&sa=t&url=https://cmnews.com.tw/article/newsyoudeservetoknow-acb08a4d-2bea-11f1-be52-d624515360f4&ct=ga&cd=CAIyHTUzZjYxZGE4MDRiOTAxMjE6Y29tOnpoLVRXOlRX&usg=AOvVaw1hPZUXcFwYZA-3ht6YX1lr",
    "published": "2026-03-30T03:46:24Z",
    "summary": "<b>啟碁</b>(<b>6285</b>)受避險情緒影響重挫，但外資大舉買超20億元，法人看好低軌衛星與800G前景。本文解析<b>啟碁</b>展望，並觀察建漢、眾達等5檔網通概念股盤中走勢，&nbsp;...",
    "stock_id": "6285",
    "name": "啟碁",
    "fetched_at": "2026-03-30T05:30:48.343850+00:00"
  },
  {
    "id": "tag:google.com,2013:googlealerts/feed:4403274584104438650",
    "title": "【即時新聞】<b>啟碁</b>最新獲外資狂掃逾萬張，低軌衛星發酵小心拉回！ - 理財寶",
    "link": "https://www.google.com/url?rct=j&sa=t&url=https://www.cmoney.tw/notes/note-detail.aspx%3Fnid%3D1156717&ct=ga&cd=CAIyHTUzZjYxZGE4MDRiOTAxMjE6Y29tOnpoLVRXOlRX&usg=AOvVaw3VJlEqUZ1vhHJmz6v-xx5-",
    "published": "2026-03-30T03:36:41Z",
    "summary": "低軌衛星需求發酵與法人觀點剖析. 近期受惠於低軌衛星題材與相關地面設備佈局，網通大廠<b>啟碁</b>(<b>6285</b>)成為台股市場關注焦點。儘管日前大盤受地緣政治與避險情緒&nbsp;...",
    "stock_id": "6285",
    "name": "啟碁",
    "fetched_at": "2026-03-30T05:30:48.343855+00:00"
  },
  {
    "id": "tag:google.com,2013:googlealerts/feed:15784114637880378867",
    "title": "【即時新聞】<b>啟碁</b>最新獲外資狂掃逾萬張，低軌衛星發酵小心拉回！",
    "link": "https://www.google.com/url?rct=j&sa=t&url=https://cmnews.com.tw/article/newsyoudeservetoknow-895c9427-2be4-11f1-95c8-d808dfa38ab6&ct=ga&cd=CAIyHTUzZjYxZGE4MDRiOTAxMjE6Y29tOnpoLVRXOlRX&usg=AOvVaw0oYYGNgX9rlw049YWCJ4IB",
    "published": "2026-03-30T03:02:05Z",
    "summary": "評價面考量：雖受惠長期衛星通訊需求帶動獲利成長，但部分法人提醒，考量股價先前累積一定漲幅，短期評價已逐漸趨近合理區間。 <b>啟碁</b>(<b>6285</b>)：近期基本面、籌碼面與技術&nbsp;...",
    "stock_id": "6285",
    "name": "啟碁",
    "fetched_at": "2026-03-30T05:30:48.343860+00:00"
  },
  {
    "id": "tag:google.com,2013:googlealerts/feed:1607327275306932148",
    "title": "低軌衛星飛不動了？「這檔」噴30%後急墜6% 仲琦、<b>啟碁</b>齊殺破7%...惟它直衝漲停達連5漲",
    "link": "https://www.google.com/url?rct=j&sa=t&url=https://tw.stock.yahoo.com/news/%25E4%25BD%258E%25E8%25BB%258C%25E8%25A1%259B%25E6%2598%259F%25E9%25A3%259B%25E4%25B8%258D%25E5%258B%2595%25E4%25BA%2586-%25E9%2580%2599%25E6%25AA%2594-%25E5%2599%25B430-%25E5%25BE%258C%25E6%2580%25A5%25E5%25A2%259C6-%25E4%25BB%25B2%25E7%2590%25A6-024000380.html&ct=ga&cd=CAIyHTUzZjYxZGE4MDRiOTAxMjE6Y29tOnpoLVRXOlRX&usg=AOvVaw1EPSc_NjV0YEXp0Kn2Kl1Z",
    "published": "2026-03-30T02:56:46Z",
    "summary": "截至10點30分，低軌衛星概念股盤中跌幅逾5%個股包含，百一（6152）暫報16.5元、跌8.33%；<b>啟碁</b>（<b>6285</b>）暫報174元、跌7.69%；仲琦（2419）暫報32.7元、跌7.63%；台光電（2383）&nbsp;...",
    "stock_id": "6285",
    "name": "啟碁",
    "fetched_at": "2026-03-30T05:30:48.343864+00:00"
  },
  {
    "id": "tag:google.com,2013:googlealerts/feed:14569650198891854038",
    "title": "低軌衛星飛不動了？「這檔」噴30%後急墜6% 仲琦、<b>啟碁</b>齊殺破7%...惟它直衝漲停達連5漲",
    "link": "https://www.google.com/url?rct=j&sa=t&url=https://www.ftnn.com.tw/news/534017&ct=ga&cd=CAIyHTUzZjYxZGE4MDRiOTAxMjE6Y29tOnpoLVRXOlRX&usg=AOvVaw2st4nQvxqT7Qm6hlYBlCiF",
    "published": "2026-03-30T02:43:03Z",
    "summary": "... <b>啟碁</b>（<b>6285</b>）則同步大跌超過7%，類股整體表現低迷，惟乙盛-KY（5243）一度攻達漲停，有望繳出連5漲的好成績。 廣告更多內容請繼續往下閱讀. 截至10點30分，低&nbsp;...",
    "stock_id": "6285",
    "name": "啟碁",
    "fetched_at": "2026-03-30T05:30:48.343868+00:00"
  },
  {
    "id": "tag:google.com,2013:googlealerts/feed:2323192519717190501",
    "title": "【台股盤前0330】低軌衛星狂潮來襲! 盤中狂跌600點、三法狂賣401億 - 永豐金證券",
    "link": "https://www.google.com/url?rct=j&sa=t&url=https://www.sinotrade.com.tw/richclub/hotopic/-%25E5%258F%25B0%25E8%2582%25A1%25E7%259B%25A4%25E5%2589%258D0330-%25E4%25BD%258E%25E8%25BB%258C%25E8%25A1%259B%25E6%2598%259F%25E7%258B%2582%25E6%25BD%25AE%25E4%25BE%2586%25E8%25A5%25B2--%25E7%259B%25A4%25E4%25B8%25AD%25E7%258B%2582%25E8%25B7%258C600%25E9%25BB%259E-%25E4%25B8%2589%25E6%25B3%2595%25E7%258B%2582%25E8%25B3%25A3401%25E5%2584%2584-%25E9%2581%25B8%25E8%2582%25A1%25E8%25BD%2589%25E5%2590%2591%25E6%258A%2595%25E6%259C%25AC%25E6%25AF%2594%25E6%258E%2592%25E8%25A1%258C%25E8%2581%259A%25E7%2584%25A6-%25E8%25A3%2595%25E8%259E%258D-%25E5%258B%25A4%25E8%25AA%25A0-%25E5%25AF%258C%25E4%25B8%2596%25E9%2581%2594-69c203aae7066762afe0c338&ct=ga&cd=CAIyHTUzZjYxZGE4MDRiOTAxMjE6Y29tOnpoLVRXOlRX&usg=AOvVaw2hx20bZ348AE7tVZ0Go4kf",
    "published": "2026-03-30T02:21:54Z",
    "summary": "籌碼分析. 外資買超金額最大的個股包括:8299群聯、2313華通、2344華邦電、<b>6285啟碁</b>、2337旺&nbsp;...",
    "stock_id": "6285",
    "name": "啟碁",
    "fetched_at": "2026-03-30T05:30:48.343872+00:00"
  },
  {
    "id": "tag:google.com,2013:googlealerts/feed:4998087853318391049",
    "title": "盤中速報- <b>啟碁</b>(<b>6285</b>)大跌7.16%，報175元| anue鉅亨網 - LINE TODAY",
    "link": "https://www.google.com/url?rct=j&sa=t&url=https://today.line.me/tw/v3/article/KwLWnGN&ct=ga&cd=CAIyHTUzZjYxZGE4MDRiOTAxMjE6Y29tOnpoLVRXOlRX&usg=AOvVaw3CLd0NuAXM_hVdb9HDnm_d",
    "published": "2026-03-30T01:54:31Z",
    "summary": "<b>啟碁</b>(<b>6285</b>-TW)30日09:50股價下跌13.5元，報175.0元，跌幅7.16%，成交18739張。 <b>啟碁</b>(<b>6285</b>-TW)所屬產...",
    "stock_id": "6285",
    "name": "啟碁",
    "fetched_at": "2026-03-30T05:30:48.343876+00:00"
  },
  {
    "id": "tag:google.com,2013:googlealerts/feed:18389296840003694475",
    "title": "3/27上市外資買超排行前20名| MoneyDJ理財網 - LINE TODAY",
    "link": "https://www.google.com/url?rct=j&sa=t&url=https://today.line.me/tw/v3/article/oqY8GXw&ct=ga&cd=CAIyHTUzZjYxZGE4MDRiOTAxMjE6Y29tOnpoLVRXOlRX&usg=AOvVaw1impp_O2et4wsfpR7t_few",
    "published": "2026-03-30T01:52:49Z",
    "summary": "... <b>6285啟碁</b>10,708 188.50 16.50 5 5871中租-KY 10,506 113.00 4.00 6 2313華通10,322 270.00 24.50 7 2337旺宏9,963 125.00 -3.00 8 2367燿華7,385 78.20 2.90&nbsp;...",
    "stock_id": "6285",
    "name": "啟碁",
    "fetched_at": "2026-03-30T05:30:48.343880+00:00"
  },
  {
    "id": "tag:google.com,2013:googlealerts/feed:8108649219005852338",
    "title": "盤中速報- <b>啟碁</b>(<b>6285</b>)大跌7.16%，報175元",
    "link": "https://www.google.com/url?rct=j&sa=t&url=https://m.cnyes.com/news/id/6400923&ct=ga&cd=CAIyHTUzZjYxZGE4MDRiOTAxMjE6Y29tOnpoLVRXOlRX&usg=AOvVaw24F_cXBeKvlfscrmKb8O_6",
    "published": "2026-03-30T01:50:31Z",
    "summary": "<b>啟碁</b>(<b>6285</b>-TW)盤中股價下跌，近5日股價、大盤表現、三大法人買賣超、融資融券增減、即時新聞資訊。",
    "stock_id": "6285",
    "name": "啟碁",
    "fetched_at": "2026-03-30T05:30:48.343884+00:00"
  },
  {
    "id": "tag:google.com,2013:googlealerts/feed:2128127513297853076",
    "title": "恐懼指數驚見10.2 滯脹幽靈引爆撤資潮！鴻海、廣達等4檔快避開拉回後下步怎麼走？",
    "link": "https://www.google.com/url?rct=j&sa=t&url=https://wantrich.chinatimes.com/news/20260330900184-420101%3Futm_source%3Dwantrich%26utm_medium%3Dtextline%26utm_campaign%3Darticle%26utm_term%3Dpromote%26utm_content%3D1&ct=ga&cd=CAIyHTUzZjYxZGE4MDRiOTAxMjE6Y29tOnpoLVRXOlRX&usg=AOvVaw0tED5QP2SkiciJ5vYzghpT",
    "published": "2026-03-30T01:37:45Z",
    "summary": "低軌衛星部分則受惠SpaceX計畫IPO帶動，昇達科、華通(2313)與耀華(2367)每年成長率預估翻倍起跳，<b>啟碁</b>(<b>6285</b>)則在Starlink地面接收站技術極強，EPS具備上修空間。",
    "stock_id": "6285",
    "name": "啟碁",
    "fetched_at": "2026-03-30T05:30:48.343888+00:00"
  },
  {
    "id": "tag:google.com,2013:googlealerts/feed:14915577726503015928",
    "title": "外資近5日買超個股 - 鉅亨網",
    "link": "https://www.google.com/url?rct=j&sa=t&url=https://news.cnyes.com/news/id/6400792&ct=ga&cd=CAIyHTUzZjYxZGE4MDRiOTAxMjE6Y29tOnpoLVRXOlRX&usg=AOvVaw1Q8gnf0QFrvdoHnYQZm7rt",
    "published": "2026-03-30T00:59:02Z",
    "summary": "5. 外資當日(27) 買超的股票復華彭博新興債(00711B-TW)、華邦電(2344-TW)、仁寶(2324-TW)、<b>啟碁</b>(<b>6285</b>-TW)、中租-KY (5871-TW). 掌握全球財經資訊點我下載APP.",
    "stock_id": "6285",
    "name": "啟碁",
    "fetched_at": "2026-03-30T05:30:48.343892+00:00"
  },
  {
    "id": "tag:google.com,2013:googlealerts/feed:12189286897054992350",
    "title": "外資近3日買超個股 - 鉅亨網",
    "link": "https://www.google.com/url?rct=j&sa=t&url=https://m.cnyes.com/news/id/6400789&ct=ga&cd=CAIyHTUzZjYxZGE4MDRiOTAxMjE6Y29tOnpoLVRXOlRX&usg=AOvVaw0Z2dCdBTrfbtsBLZ7eX_D4",
    "published": "2026-03-30T00:47:52Z",
    "summary": "(2344-TW)、仁寶(2324-TW)、<b>啟碁</b>(<b>6285</b>-TW)、中租-KY (5871-TW). 掌握全球財經資訊點我下載APP. ‌. 文章標籤. 台股台股盤後表格 更多 arrow-icon. 5 月報稅倒數！",
    "stock_id": "6285",
    "name": "啟碁",
    "fetched_at": "2026-03-30T05:30:48.343896+00:00"
  },
  {
    "id": "tag:google.com,2013:googlealerts/feed:771711297396673820",
    "title": "通膨再現？台股再跌6000點？接下來，你必須知道的事！ | 鉅亨網- 專家觀點",
    "link": "https://www.google.com/url?rct=j&sa=t&url=https://m.cnyes.com/news/id/6400758&ct=ga&cd=CAIyHTUzZjYxZGE4MDRiOTAxMjE6Y29tOnpoLVRXOlRX&usg=AOvVaw3Y5FwICgdfHoKnkd-3yL79",
    "published": "2026-03-30T00:32:55Z",
    "summary": "還有<b>啟碁</b>(<b>6285</b>-TW)，它在Starlink 地面接收站技術極強，今年EPS 估9-11 元，但衛星商用化一加速，比重拉高，EPS 就會往上調。 3. 散熱與載板：AI 算力的基礎&nbsp;...",
    "stock_id": "6285",
    "name": "啟碁",
    "fetched_at": "2026-03-30T05:30:48.343900+00:00"
  },
  {
    "id": "tag:google.com,2013:googlealerts/feed:11139556506430126335",
    "title": "投信個股：上週五(27日)投信買超／賣超個股一覽表 - 富聯網",
    "link": "https://www.google.com/url?rct=j&sa=t&url=https://ww2.money-link.com.tw/realtimenews/NewsContent.aspx%3FSN%3D2343408002%26PU%3D0008&ct=ga&cd=CAIyHTUzZjYxZGE4MDRiOTAxMjE6Y29tOnpoLVRXOlRX&usg=AOvVaw3yn05P9kAmJwQn8RFdo-Tq",
    "published": "2026-03-30T00:27:59Z",
    "summary": "<b>6285 啟碁</b>158. 賣超張數如下：. 代號個股張數. 2324 仁寶20,891. 1303 南亞8,985. 2408 南亞科7,434. 2344 華邦電6,084. 2337 旺宏2,588. 2449 京元電子1,954.",
    "stock_id": "6285",
    "name": "啟碁",
    "fetched_at": "2026-03-30T05:30:48.343905+00:00"
  },
  {
    "id": "tag:google.com,2013:googlealerts/feed:10614450586516971168",
    "title": "外資個股：上週五(27日)外資買超／賣超個股一覽表 - 富聯網",
    "link": "https://www.google.com/url?rct=j&sa=t&url=https://ww2.money-link.com.tw/RealtimeNews/NewsContent.aspx%3FSN%3D2343407002%26PU%3D0010&ct=ga&cd=CAIyHTUzZjYxZGE4MDRiOTAxMjE6Y29tOnpoLVRXOlRX&usg=AOvVaw0ELkkpWr0bzKVGdG7bhxk5",
    "published": "2026-03-30T00:01:48Z",
    "summary": "買超張數如下：. 代號個股張數. 00711B 復華彭博新興債133,825. 2344 華邦電24,119. 2324 仁寶22,460. <b>6285 啟碁</b>10,707. 5871 中租-KY 10,506.",
    "stock_id": "6285",
    "name": "啟碁",
    "fetched_at": "2026-03-30T05:30:48.343908+00:00"
  },
  {
    "id": "tag:google.com,2013:googlealerts/feed:17431094618059118563",
    "title": "《外資》買超股：華邦電、中租-KY、王道銀行 - 旺得富理財網",
    "link": "https://www.google.com/url?rct=j&sa=t&url=https://wantrich.chinatimes.com/news/20260330900030-420101&ct=ga&cd=CAIyHTUzZjYxZGE4MDRiOTAxMjE6Y29tOnpoLVRXOlRX&usg=AOvVaw35V2D43WZVYczyTJtHn202",
    "published": "2026-03-29T23:52:57Z",
    "summary": "... <b>啟碁</b>(<b>6285</b>) 華通(2313) 旺宏(2337) &middot; 燿華(2367) 建漢(3062) 擎亞(8096) 英業達(2356) 定穎投控(3715) &middot; 遠傳(4904) 禾伸堂(3026). 傳產股：. 中租-KY(5871) 長榮&nbsp;...",
    "stock_id": "6285",
    "name": "啟碁",
    "fetched_at": "2026-03-30T05:30:48.343913+00:00"
  },
  {
    "id": "tag:google.com,2013:googlealerts/feed:7030698092045562661",
    "title": "3/27上市外資買超排行前20名- 新聞- MoneyDJ理財網",
    "link": "https://www.google.com/url?rct=j&sa=t&url=https://www.moneydj.com/KMDJ/news/newsviewer.aspx%3Fa%3D7ddc4f1d-1d0f-4079-864f-a02b08942f2a&ct=ga&cd=CAIyHTUzZjYxZGE4MDRiOTAxMjE6Y29tOnpoLVRXOlRX&usg=AOvVaw3qFVuesZ2XZPxmnJzQqhMu",
    "published": "2026-03-29T23:46:38Z",
    "summary": "<b>6285啟碁</b>, 10,708, 188.50, 16.50. 5, 5871中租-KY, 10,506, 113.00, 4.00. 6, 2313華通, 10,322, 270.00, 24.50. 7, 2337旺宏, 9,963, 125.00, -3.00. 8, 2367&nbsp;...",
    "stock_id": "6285",
    "name": "啟碁",
    "fetched_at": "2026-03-30T05:30:48.343917+00:00"
  },
  {
    "id": "tag:google.com,2013:googlealerts/feed:4634818410991712269",
    "title": "3/27上市融資增加排行前20名- 新聞- MoneyDJ理財網",
    "link": "https://www.google.com/url?rct=j&sa=t&url=http://www.moneydj.com/kmdj/news/newsviewer.aspx%3Fa%3D3b47c14e-8398-4b78-984d-2961cc3edc1f&ct=ga&cd=CAIyHTUzZjYxZGE4MDRiOTAxMjE6Y29tOnpoLVRXOlRX&usg=AOvVaw3MBW84OlgFZPrt-jdTCVS9",
    "published": "2026-03-29T23:46:36Z",
    "summary": "19, <b>6285啟碁</b>, 1,244, 188.50, 16.50 ; 20, 1314中石化, 1,140, 8.11, -0.19&nbsp;...",
    "stock_id": "6285",
    "name": "啟碁",
    "fetched_at": "2026-03-30T05:30:48.343921+00:00"
  },
  {
    "id": "tag:google.com,2013:googlealerts/feed:17532092245026550595",
    "title": "晨間解析：國際股市壓力仍在，週一台股依然震盪 - 富聯網",
    "link": "https://www.google.com/url?rct=j&sa=t&url=https://ww2.money-link.com.tw/realtimenews/NewsContent.aspx%3FSN%3D2343277002%26PU%3D0031&ct=ga&cd=CAIyHTUzZjYxZGE4MDRiOTAxMjE6Y29tOnpoLVRXOlRX&usg=AOvVaw1uvL2n3otGIsJLoa7uhDlE",
    "published": "2026-03-29T23:27:39Z",
    "summary": "玻纖布的富喬(1815)、建榮(5340)股價也都有表現。 低軌道衛星股上週五表現相對強勢，除了PCB的華通、燿華股價大漲外，<b>啟碁</b>(<b>6285</b>)、&nbsp;...",
    "stock_id": "6285",
    "name": "啟碁",
    "fetched_at": "2026-03-30T05:30:48.343925+00:00"
  },
  {
    "id": "tag:google.com,2013:googlealerts/feed:8346352666799936230",
    "title": "<b>6285 啟碁</b>- 昨天是否在山頂買了啟雞- 股市爆料同學會 - 理財寶",
    "link": "https://www.google.com/url?rct=j&sa=t&url=https://www.cmoney.tw/forum/article/177791092&ct=ga&cd=CAIyHTUzZjYxZGE4MDRiOTAxMjE6Y29tOnpoLVRXOlRX&usg=AOvVaw0ygd0iKl0S9WMv1gFgW-Zp",
    "published": "2026-03-30T06:47:20Z",
    "summary": "關於同學詢問的   <b>啟碁</b>(<b>6285</b>)：. 先不加碼、先不殺低。目前屬於「箱型震盪」，均線多排尚未破壞。 啟碁盤中的「角力點」？ 大環境壓制： 費半重挫、台積電領跌，觸發&nbsp;...",
    "stock_id": "6285",
    "name": "啟碁",
    "fetched_at": "2026-03-30T08:23:25.167614+00:00"
  },
  {
    "id": "tag:google.com,2013:googlealerts/feed:708302655866661241",
    "title": "《台北股市》三大法人27日買超股：華邦電、華通、旺宏",
    "link": "https://www.google.com/url?rct=j&sa=t&url=https://tw.stock.yahoo.com/news/%25E5%258F%25B0%25E5%258C%2597%25E8%2582%25A1%25E5%25B8%2582-%25E4%25B8%2589%25E5%25A4%25A7%25E6%25B3%2595%25E4%25BA%25BA27%25E6%2597%25A5%25E8%25B2%25B7%25E8%25B6%2585%25E8%2582%25A1-%25E8%258F%25AF%25E9%2582%25A6%25E9%259B%25BB-%25E8%258F%25AF%25E9%2580%259A-%25E6%2597%25BA%25E5%25AE%258F-234622225.html&ct=ga&cd=CAIyHTUzZjYxZGE4MDRiOTAxMjE6Y29tOnpoLVRXOlRX&usg=AOvVaw3dssEVrLsoxB2Fn-bLRw7i",
    "published": "2026-03-30T05:53:07Z",
    "summary": "... <b>啟碁</b>(<b>6285</b>)、中租-KY(5871)，其他依序為燿華(2367)、長榮航(2618)、建漢(3062)、玉山金(2884)及王道銀行(2897)。 至於前十大個股中買超金額前三大，則為華通&nbsp;...",
    "stock_id": "6285",
    "name": "啟碁",
    "fetched_at": "2026-03-30T08:23:25.167626+00:00"
  },
  {
    "id": "tag:google.com,2013:googlealerts/feed:5130823069396346041",
    "title": "2330 台積電- 是清算還是重洗？ - 股市爆料同學會",
    "link": "https://www.google.com/url?rct=j&sa=t&url=https://www.cmoney.tw/forum/article/177793397&ct=ga&cd=CAIyHTUzZjYxZGE4MDRiOTAxMjE6Y29tOnpoLVRXOlRX&usg=AOvVaw0qtMJZg1o-OaTayUV6zwfP",
    "published": "2026-03-30T05:27:38Z",
    "summary": "關於同學詢問的   <b>啟碁</b>(<b>6285</b>)：. 先不加碼、先不殺低。目前屬於「箱型震盪」，均線多排尚未破壞。 啟碁盤中的「角力點」？ 大環境壓制： 費半重挫、台積電領跌，觸發&nbsp;...",
    "stock_id": "6285",
    "name": "啟碁",
    "fetched_at": "2026-03-30T08:23:25.167631+00:00"
  },
  {
    "id": "tag:google.com,2013:googlealerts/feed:77566082024036377",
    "title": "盤中速報- 雍智科技(6683)大漲7.22%，報1485元| 鉅亨網",
    "link": "https://www.google.com/url?rct=j&sa=t&url=https://m.cnyes.com/news/id/6401111&ct=ga&cd=CAIyHTUzZjYxZGE4MDRiOTAxMjE6Y29tOnpoLVRXOlRX&usg=AOvVaw20-DYKhexFXerr_ntKCwo7",
    "published": "2026-03-30T03:50:24Z",
    "summary": "盤中速報- <b>啟碁</b>(<b>6285</b>)大跌7.16%，報175元. tab-icon. 其他. tab-icon save new tip. chat-icon 0. ‌. 推薦閱讀. 野村投信2026年&nbsp;...",
    "stock_id": "6285",
    "name": "啟碁",
    "fetched_at": "2026-03-30T08:23:25.167639+00:00"
  },
  {
    "id": "tag:google.com,2013:googlealerts/feed:4777822272451764983",
    "title": "<b>6285</b>(<b>啟碁</b>)股價急跌至179.50元，壓低幅度達到4.79%。 - 富聯網",
    "link": "https://www.google.com/url?rct=j&sa=t&url=https://ww2.money-link.com.tw/RealtimeNews/NewsContent.aspx%3Fsn%3D211403030%26pu%3DNews_0046&ct=ga&cd=CAIyHTUzZjYxZGE4MDRiOTAxMjE6Y29tOnpoLVRXOlRX&usg=AOvVaw1d_PpX8Qn-Cyzi5OKOFgVO",
    "published": "2026-03-30T03:17:42Z",
    "summary": "近5日股價上漲8.65%，集中市場加權股價指數下跌-1.29%，留意股價是否已經漲多伺機逢低再作布局。 &lt;近期相關新聞&gt;. 股利：<b>啟碁</b>(<b>6285</b>)今年擬發放現金股利4.3000元，殖&nbsp;...",
    "stock_id": "6285",
    "name": "啟碁",
    "fetched_at": "2026-03-30T08:23:25.167651+00:00"
  },
  {
    "id": "tag:google.com,2013:googlealerts/feed:4700099872217999917",
    "title": "3/30證交所盤後定價交易成交金額前20名排行| MoneyDJ理財網 - LINE TODAY",
    "link": "https://www.google.com/url?rct=j&sa=t&url=https://today.line.me/tw/v3/article/oqYwOQo&ct=ga&cd=CAIyHTUzZjYxZGE4MDRiOTAxMjE6Y29tOnpoLVRXOlRX&usg=AOvVaw37_1ix5KtOZH8R9oWZxjGZ",
    "published": "2026-03-30T10:41:25Z",
    "summary": "<b>6285</b>. <b>啟碁</b>. 84. 15,036,000. 179. 2308. 台達電. 10. 14,850,000. 1485. 8046. 南電. 25. 14,500,000. 580. 00919. 群益台灣精選高息. 591. 13,179,300. 22.3.",
    "stock_id": "6285",
    "name": "啟碁",
    "fetched_at": "2026-03-30T11:56:40.925706+00:00"
  },
  {
    "id": "tag:google.com,2013:googlealerts/feed:13242549999312638044",
    "title": "歷史級崩盤訊號已亮紅燈？這種股票再不賣，財富將大縮水？！ | 台股| 鉅亨號",
    "link": "https://www.google.com/url?rct=j&sa=t&url=https://hao.cnyes.com/post/239873&ct=ga&cd=CAIyHTUzZjYxZGE4MDRiOTAxMjE6Y29tOnpoLVRXOlRX&usg=AOvVaw0cSA8__KbhiFV6gxJGPm7q",
    "published": "2026-03-30T09:54:05Z",
    "summary": "... 【<b>6285啟碁</b>】Starlink地面接收站重要供應鏈，衛星需求一爆發，EPS可能直接上修。  第三：AI散熱＋載板AI晶片越強，熱度越恐怖，散熱就是剛需。【3324雙鴻】液&nbsp;...",
    "stock_id": "6285",
    "name": "啟碁",
    "fetched_at": "2026-03-30T11:56:40.925716+00:00"
  },
  {
    "id": "tag:google.com,2013:googlealerts/feed:4230366764327254722",
    "title": "3/30證交所盤後定價交易成交金額前20名排行",
    "link": "https://www.google.com/url?rct=j&sa=t&url=https://www.moneydj.com/kmdj/news/newsviewer.aspx%3Fa%3Deb2d76be-6c30-4d40-b4a3-ca3770965fec&ct=ga&cd=CAIyHTUzZjYxZGE4MDRiOTAxMjE6Y29tOnpoLVRXOlRX&usg=AOvVaw3VHQpafZ7YPFXQuX2QZpMI",
    "published": "2026-03-30T08:53:56Z",
    "summary": "<b>6285</b>. <b>啟碁</b>. 84. 15,036,000. 179. 2308. 台達電. 10. 14,850,000. 1485. 8046. 南電. 25. 14,500,000. 580. 00919. 群益台灣精選&nbsp;...",
    "stock_id": "6285",
    "name": "啟碁",
    "fetched_at": "2026-03-30T11:56:40.925721+00:00"
  },
  {
    "id": "tag:google.com,2013:googlealerts/feed:11407558040066676970",
    "title": "【即時新聞】建漢近日飆逾7%，低軌衛星發酵外資狂掃這「4檔網通股」！ | CMoney投資網誌",
    "link": "https://www.google.com/url?rct=j&sa=t&url=https://cmnews.com.tw/article/newsyoudeservetoknow-31f2543c-2be0-11f1-bd18-827e6fe1e9df&ct=ga&cd=CAIyHTUzZjYxZGE4MDRiOTAxMjE6Y29tOnpoLVRXOlRX&usg=AOvVaw2lW0wkpNv4BEjf8VOnI8n5",
    "published": "2026-03-30T02:32:07Z",
    "summary": "身為鴻海集團旗下的網通設備廠，該公司在低軌衛星的地面設備佈局成為市場焦點，與<b>啟碁</b>(<b>6285</b>)、金寶(2312)及明泰(3380)等大廠並列為關鍵受惠股。受相關題材&nbsp;...",
    "stock_id": "6285",
    "name": "啟碁",
    "fetched_at": "2026-03-30T11:56:40.925768+00:00"
  }
]