[
  {
    "id": "tag:google.com,2013:googlealerts/feed:3473836034797684056",
    "title": "投信近3日賣超個股",
    "link": "https://www.google.com/url?rct=j&sa=t&url=https://news.cnyes.com/news/print/6405221&ct=ga&cd=CAIyHWVhMjk0Y2MzNjllNDk5OGE6Y29tOnpoLVRXOlRX&usg=AOvVaw2LTVDVTK6DvJ0MhH7tztV2",
    "published": "2026-04-02T11:58:45Z",
    "summary": "1. 投信累計賣超3 日的股票仁寶(2324-TW)、南亞科(2408-TW)、旺宏(2337-TW)、<b>中華電</b>(<b>2412</b>-TW)、景碩(3189-TW). 2. 投信累計賣超2 日的股票南亞科(2408-TW)、&nbsp;...",
    "stock_id": "2412",
    "name": "中華電",
    "fetched_at": "2026-04-02T16:04:43.980772+00:00"
  },
  {
    "id": "tag:google.com,2013:googlealerts/feed:2024104274009229921",
    "title": "金鐘男星不明原因發燒…醒來食性大變！到廟裡拜拜才知「被鬼跟」 - 股市爆料同學會 - 理財寶",
    "link": "https://www.google.com/url?rct=j&sa=t&url=https://www.cmoney.tw/forum/article/177886844&ct=ga&cd=CAIyHWVhMjk0Y2MzNjllNDk5OGE6Y29tOnpoLVRXOlRX&usg=AOvVaw1wvVN2qeCzePKe3_Ikq7v3",
    "published": "2026-04-02T11:21:21Z",
    "summary": "<b>中華電</b>. <b>2412</b>. 133. 1 (-0.75%). 台股最新. 2 天前 投資網誌. 【10:19 即時新聞】聯策(6658)股價上漲逾8%，CPO與先進封裝題材點火，短中期多頭結構支撐買盤迴流.",
    "stock_id": "2412",
    "name": "中華電",
    "fetched_at": "2026-04-02T16:04:43.980784+00:00"
  },
  {
    "id": "tag:google.com,2013:googlealerts/feed:6115712406586628455",
    "title": "【04/01 法人動向】三大法人買超台股550.09億元 - CMoney投資網誌",
    "link": "https://www.google.com/url?rct=j&sa=t&url=https://cmnews.com.tw/article/cmoneyaicurator-f3234a4f-2e70-11f1-837d-4129aae2eda0&ct=ga&cd=CAIyHWVhMjk0Y2MzNjllNDk5OGE6Y29tOnpoLVRXOlRX&usg=AOvVaw3VgauDME6apVRf_fv829OB",
    "published": "2026-04-02T08:54:25Z",
    "summary": "<b>中華電</b>(<b>2412</b>) 3,033.69張*已連續2日賣超. 【自營商買賣超前三名】 買超： 1. 群創(3481) 4,135.67張*由賣超初轉買超 2. 南亞(1303) 4,114.46張*由賣超初轉買&nbsp;...",
    "stock_id": "2412",
    "name": "中華電",
    "fetched_at": "2026-04-02T16:04:43.980789+00:00"
  },
  {
    "id": "tag:google.com,2013:googlealerts/feed:15457283284832092190",
    "title": "【04/01 法人動向】三大法人買超台股550.09億元 - 理財寶",
    "link": "https://www.google.com/url?rct=j&sa=t&url=https://www.cmoney.tw/notes/note-detail.aspx%3Fnid%3D1159346&ct=ga&cd=CAIyHWVhMjk0Y2MzNjllNDk5OGE6Y29tOnpoLVRXOlRX&usg=AOvVaw2K13PtiqHpYR5edRdOKY_0",
    "published": "2026-04-02T08:52:52Z",
    "summary": "... <b>中華電</b>(<b>2412</b>) 3,033.69張*已連續2日賣超. 【自營商買賣超前三名】 買超： 1. 群創(3481) 4,135.67張*由賣超初轉買超 2. 南亞(1303) 4,114.46張*由賣超初轉&nbsp;...",
    "stock_id": "2412",
    "name": "中華電",
    "fetched_at": "2026-04-02T16:04:43.980794+00:00"
  },
  {
    "id": "tag:google.com,2013:googlealerts/feed:14769241628122745188",
    "title": "年化配息率飆12%！00905季配0.6元最後買進日快筆記「這招」選股策略反彈狂勝0050",
    "link": "https://www.google.com/url?rct=j&sa=t&url=https://www.ftnn.com.tw/news/534902&ct=ga&cd=CAIyHWVhMjk0Y2MzNjllNDk5OGE6Y29tOnpoLVRXOlRX&usg=AOvVaw0MHokJC37PCUgE-xnDaXF1",
    "published": "2026-04-02T08:09:14Z",
    "summary": "... <b>中華電</b>（<b>2412</b>）2.74%、富邦金（2881）2.72%、國泰金（2882）2.62%。 此外，00905並非單純依賴收益平準金來支撐配息，而是透過選股創造資本利得作為配息基礎&nbsp;...",
    "stock_id": "2412",
    "name": "中華電",
    "fetched_at": "2026-04-02T16:04:43.980798+00:00"
  },
  {
    "id": "tag:google.com,2013:googlealerts/feed:9552935708633639551",
    "title": "近期召開國內、外法說會之上市櫃公司一覽表 - 富聯網",
    "link": "https://www.google.com/url?rct=j&sa=t&url=https://ww2.money-link.com.tw/RealtimeNews/NewsContent.aspx%3Fsn%3D2345195002%26pu%3DNews_0009_3&ct=ga&cd=CAIyHWVhMjk0Y2MzNjllNDk5OGE6Y29tOnpoLVRXOlRX&usg=AOvVaw2QmWTqOJDSQQcqUSoJx2Am",
    "published": "2026-04-02T01:24:41Z",
    "summary": "5/07 <b>中華電</b>(<b>2412</b>). 近期召開「國外法說會」之上市櫃公司及時程如下：. 4/07-4/09 緯創(3231). 4/14-4/15 光寶科(2301). 4/14-4/16 台達電(2308)、宏碁(2353)&nbsp;...",
    "stock_id": "2412",
    "name": "中華電",
    "fetched_at": "2026-04-02T16:04:43.980802+00:00"
  },
  {
    "id": "tag:google.com,2013:googlealerts/feed:4597144497122830118",
    "title": "4/1上市投信賣超排行前20名| MoneyDJ理財網 - LINE TODAY",
    "link": "https://www.google.com/url?rct=j&sa=t&url=https://today.line.me/tw/v3/article/VxXnx9L&ct=ga&cd=CAIyHWVhMjk0Y2MzNjllNDk5OGE6Y29tOnpoLVRXOlRX&usg=AOvVaw0jQZFh95axH1OQO-g2iR-D",
    "published": "2026-04-02T01:08:42Z",
    "summary": "... <b>2412中華電</b>-3,034 134.00 1.00 243 3,277 4 2408南亞科-2,141 211.00 12.50 7 2,148 5 3189景碩-2,127 332.00 19.00 5 2,132 6 3715定穎投控-1,355 180.00&nbsp;...",
    "stock_id": "2412",
    "name": "中華電",
    "fetched_at": "2026-04-02T16:04:43.980806+00:00"
  },
  {
    "id": "tag:google.com,2013:googlealerts/feed:14522556673860539799",
    "title": "投信近5日賣超個股 - 鉅亨網",
    "link": "https://www.google.com/url?rct=j&sa=t&url=https://news.cnyes.com/news/id/6405224&ct=ga&cd=CAIyHWVhMjk0Y2MzNjllNDk5OGE6Y29tOnpoLVRXOlRX&usg=AOvVaw0zY1KD-QEIIn3uxy9aUinP",
    "published": "2026-04-02T00:49:39Z",
    "summary": ")、主動復華未來50 (00991A-TW)、<b>中華電</b>(<b>2412</b>-TW). 2. 投信累計賣超4 日的股票仁寶(2324-TW)、南亞科(2408-TW)、旺宏(2337-TW)、京元電子(2449-TW)、<b>中華電</b>(<b>2412</b>&nbsp;...",
    "stock_id": "2412",
    "name": "中華電",
    "fetched_at": "2026-04-02T16:04:43.980810+00:00"
  },
  {
    "id": "tag:google.com,2013:googlealerts/feed:12131606646070247012",
    "title": "投信近5日賣超個股| anue鉅亨網 - LINE TODAY",
    "link": "https://www.google.com/url?rct=j&sa=t&url=https://today.line.me/tw/v3/article/kEoQEVJ&ct=ga&cd=CAIyHWVhMjk0Y2MzNjllNDk5OGE6Y29tOnpoLVRXOlRX&usg=AOvVaw2MnKoSFTPU2lXj-9oKQrhA",
    "published": "2026-04-02T00:49:17Z",
    "summary": "1. 投信累計賣超5 日的股票仁寶(2324-TW)、南亞科(2408-TW)、旺宏(2337-TW)、主動復華未來50 (00991A-TW)、<b>中華電</b>(<b>2412</b>-TW).",
    "stock_id": "2412",
    "name": "中華電",
    "fetched_at": "2026-04-02T16:04:43.980814+00:00"
  },
  {
    "id": "tag:google.com,2013:googlealerts/feed:3064203133737373791",
    "title": "投信近5日賣超個股 - 鉅亨網",
    "link": "https://www.google.com/url?rct=j&sa=t&url=https://m.cnyes.com/news/id/6405224&ct=ga&cd=CAIyHWVhMjk0Y2MzNjllNDk5OGE6Y29tOnpoLVRXOlRX&usg=AOvVaw1KPR85oZQGCrvQjowRNnmb",
    "published": "2026-04-02T00:46:55Z",
    "summary": "1. 投信累計賣超5 日的股票仁寶(2324-TW)、南亞科(2408-TW)、旺宏(2337-TW)、主動復華未來50 (00991A-TW)、<b>中華電</b>(<b>2412</b>-TW).",
    "stock_id": "2412",
    "name": "中華電",
    "fetched_at": "2026-04-02T16:04:43.980818+00:00"
  },
  {
    "id": "tag:google.com,2013:googlealerts/feed:5618102232623462674",
    "title": "投信近3日賣超個股 - 鉅亨網",
    "link": "https://www.google.com/url?rct=j&sa=t&url=https://m.cnyes.com/news/id/6405221&ct=ga&cd=CAIyHWVhMjk0Y2MzNjllNDk5OGE6Y29tOnpoLVRXOlRX&usg=AOvVaw0mGHy-ky2MWiBWXlHUVM77",
    "published": "2026-04-02T00:44:43Z",
    "summary": "投信累計賣超3 日的股票仁寶(2324-TW)、南亞科(2408-TW)、旺宏(2337-TW)、<b>中華電</b>(<b>2412</b>-TW)、景碩(3189-TW). 2. 投信累計賣超2 日的股票南亞科(2408-TW)、&nbsp;...",
    "stock_id": "2412",
    "name": "中華電",
    "fetched_at": "2026-04-02T16:04:43.980822+00:00"
  },
  {
    "id": "tag:google.com,2013:googlealerts/feed:5141569357470429901",
    "title": "4/1上市投信賣超排行前20名 - Yahoo股市",
    "link": "https://www.google.com/url?rct=j&sa=t&url=https://tw.stock.yahoo.com/news/4-1%25E4%25B8%258A%25E5%25B8%2582%25E6%258A%2595%25E4%25BF%25A1%25E8%25B3%25A3%25E8%25B6%2585%25E6%258E%2592%25E8%25A1%258C%25E5%2589%258D20%25E5%2590%258D-233100418.html&ct=ga&cd=CAIyHWVhMjk0Y2MzNjllNDk5OGE6Y29tOnpoLVRXOlRX&usg=AOvVaw3QMjMiUZhCNQkibO_rL0Sw",
    "published": "2026-04-02T00:42:42Z",
    "summary": "名次股票名稱買賣超張數收盤價漲跌買進張數賣出張數1 2344華邦電-6638 93.10 2.90 1133 7771 2 2303聯電-4123 57.40 0.90 3185 7308 3 <b>2412中華電</b>-3034&nbsp;...",
    "stock_id": "2412",
    "name": "中華電",
    "fetched_at": "2026-04-02T16:04:43.980826+00:00"
  },
  {
    "id": "tag:google.com,2013:googlealerts/feed:3672988104110868275",
    "title": "《台北股市》投信01日賣超股：華邦電、聯電、<b>中華電</b> - 永豐金證券",
    "link": "https://www.google.com/url?rct=j&sa=t&url=https://www.sinotrade.com.tw/richclub/news/69cdb1aab4c4296334756ebd&ct=ga&cd=CAIyHWVhMjk0Y2MzNjllNDk5OGE6Y29tOnpoLVRXOlRX&usg=AOvVaw0Me6_T8e7We1qKXswoSdOk",
    "published": "2026-04-02T00:28:31Z",
    "summary": "<b>中華電</b>(<b>2412</b>)收134.00元，漲1.00元或0.75%，成交量1.06萬張，投信賣超3033張、估4.07億元，為連2日賣超，累計賣超6394張、估8.54億元。 4.南亞科(2408)收&nbsp;...",
    "stock_id": "2412",
    "name": "中華電",
    "fetched_at": "2026-04-02T16:04:43.980830+00:00"
  },
  {
    "id": "tag:google.com,2013:googlealerts/feed:12438666349048158186",
    "title": "【台股盤前0402】記憶體模組絕地大反彈！CCL緊握題材持續強漲! 「多頭趨勢實戶買」：華通",
    "link": "https://www.google.com/url?rct=j&sa=t&url=https://www.sinotrade.com.tw/richclub/hotopic/-%25E5%258F%25B0%25E8%2582%25A1%25E7%259B%25A4%25E5%2589%258D0402-%25E8%25A8%2598%25E6%2586%25B6%25E9%25AB%2594%25E6%25A8%25A1%25E7%25B5%2584%25E7%25B5%2595%25E5%259C%25B0%25E5%25A4%25A7%25E5%258F%258D%25E5%25BD%2588-CCL%25E7%25B7%258A%25E6%258F%25A1%25E9%25A1%258C%25E6%259D%2590%25E6%258C%2581%25E7%25BA%258C%25E5%25BC%25B7%25E6%25BC%25B2---%25E5%25A4%259A%25E9%25A0%25AD%25E8%25B6%25A8%25E5%258B%25A2%25E5%25AF%25A6%25E6%2588%25B6%25E8%25B2%25B7--%25E8%258F%25AF%25E9%2580%259A-%25E7%25A9%25A9%25E6%2587%258B-%25E8%2581%25AF%25E8%258C%2582-69ca3620e32a6662e60cec8a&ct=ga&cd=CAIyHWVhMjk0Y2MzNjllNDk5OGE6Y29tOnpoLVRXOlRX&usg=AOvVaw2euFXdFyCZehaVuc8M5tws",
    "published": "2026-04-02T00:10:47Z",
    "summary": "投信賣超金額最大的個股包括:3189景碩、2344華邦電、2408南亞科、<b>2412中華電</b>、6515穎崴。 三大法人同買金額最大的個股包括:2330台積電、2368金像電、2308台&nbsp;...",
    "stock_id": "2412",
    "name": "中華電",
    "fetched_at": "2026-04-02T16:04:43.980834+00:00"
  },
  {
    "id": "tag:google.com,2013:googlealerts/feed:5791647380330272029",
    "title": "4/1上市投信賣超排行前20名- 新聞- MoneyDJ理財網",
    "link": "https://www.google.com/url?rct=j&sa=t&url=https://www.moneydj.com/kmdj/news/newsviewer.aspx%3Fa%3Dfb75e07e-c3b3-445a-ae5f-59dcaa2253d2&ct=ga&cd=CAIyHWVhMjk0Y2MzNjllNDk5OGE6Y29tOnpoLVRXOlRX&usg=AOvVaw1FSx1SfrbadSMzkvEPkQin",
    "published": "2026-04-02T00:08:47Z",
    "summary": "<b>2412中華電</b>, -3,034, 134.00, 1.00, 243, 3,277. 4, 2408南亞科, -2,141, 211.00, 12.50, 7, 2,148. 5, 3189景碩, -2,127, 332.00, 19.00, 5, 2,132. 6, 3715定&nbsp;...",
    "stock_id": "2412",
    "name": "中華電",
    "fetched_at": "2026-04-02T16:04:43.980838+00:00"
  },
  {
    "id": "tag:google.com,2013:googlealerts/feed:18380948344147090337",
    "title": "《台北股市》投信01日賣超股：華邦電、聯電、<b>中華電</b> - 富聯網",
    "link": "https://www.google.com/url?rct=j&sa=t&url=https://ww2.money-link.com.tw/RealtimeNews/NewsContent.aspx%3Fsn%3D6127546001%26pu%3DNews_0046&ct=ga&cd=CAIyHWVhMjk0Y2MzNjllNDk5OGE6Y29tOnpoLVRXOlRX&usg=AOvVaw2BBLKDHWlyOV7Ts7YAyqxK",
    "published": "2026-04-01T23:54:29Z",
    "summary": "3.<b>中華電</b>(<b>2412</b>)收134.00元，漲1.00元或0.75%，成交量1.06萬張，投信賣超3033張、估4.07&nbsp;...",
    "stock_id": "2412",
    "name": "中華電",
    "fetched_at": "2026-04-02T16:04:43.980842+00:00"
  },
  {
    "id": "tag:google.com,2013:googlealerts/feed:8607809446641920143",
    "title": "《外資》買超股：兆豐金、智擎、萬海- 上市櫃 - 旺得富理財網",
    "link": "https://www.google.com/url?rct=j&sa=t&url=https://wantrich.chinatimes.com/news/20260402900030-420101&ct=ga&cd=CAIyHWVhMjk0Y2MzNjllNDk5OGE6Y29tOnpoLVRXOlRX&usg=AOvVaw1TRGmeExeQ5fGjOoaAv5SU",
    "published": "2026-04-01T23:46:08Z",
    "summary": "... <b>中華電</b>(<b>2412</b>) &middot; 網家(8044) 中信金(2891) 南亞(1303) 寶成(9904) 興富發(2542) &middot; 亞泥(1102) 佳世達(2352) 宏達電(2498) 新普(6121) 日月光投控(3711) &middot; 工信(&nbsp;...",
    "stock_id": "2412",
    "name": "中華電",
    "fetched_at": "2026-04-02T16:04:43.980846+00:00"
  },
  {
    "id": "tag:google.com,2013:googlealerts/feed:5033603804010306448",
    "title": "《外資》買超股：兆豐金、智擎、萬海 - 富聯網",
    "link": "https://www.google.com/url?rct=j&sa=t&url=https://ww2.money-link.com.tw/RealtimeNews/NewsContent.aspx%3FSN%3D6127531001%26PU%3D0010&ct=ga&cd=CAIyHWVhMjk0Y2MzNjllNDk5OGE6Y29tOnpoLVRXOlRX&usg=AOvVaw1bJdCmapNRQ5J3yzTS3k8r",
    "published": "2026-04-01T23:44:25Z",
    "summary": "轉賣為買的股票：. 櫻花(9911) 正新(2105) 台積電(2330) 鴻海(2317) <b>中華電</b>(<b>2412</b>). 網家(8044) 中信金(2891) 南亞(1303) 寶成(9904) 興富發(2542). 亞泥(1102)&nbsp;...",
    "stock_id": "2412",
    "name": "中華電",
    "fetched_at": "2026-04-02T16:04:43.980850+00:00"
  },
  {
    "id": "tag:google.com,2013:googlealerts/feed:13571903732432172968",
    "title": "中華電信降價，寬頻市場激戰 - 理財寶",
    "link": "https://www.google.com/url?rct=j&sa=t&url=https://www.cmoney.tw/forum/article/177866885&ct=ga&cd=CAIyHWVhMjk0Y2MzNjllNDk5OGE6Y29tOnpoLVRXOlRX&usg=AOvVaw3ZOZR0RXfkgl6vXlx9d7Kq",
    "published": "2026-04-01T22:17:05Z",
    "summary": "心得：<b>中華電</b>光纖降價，這波會讓有線電視哭了吧？---中華電信（<b>2412</b>）面對電信、有線電視業者在寬頻市場的積極競爭，強調以高速光纖網路與資費促銷方案守住市場。",
    "stock_id": "2412",
    "name": "中華電",
    "fetched_at": "2026-04-02T16:04:43.980854+00:00"
  },
  {
    "id": "tag:google.com,2013:googlealerts/feed:17803980471139057379",
    "title": "中華電信ADR1日上漲0.15美元漲幅0.36%折台股135.43元 - Yahoo股市",
    "link": "https://www.google.com/url?rct=j&sa=t&url=https://tw.stock.yahoo.com/news/%25E4%25B8%25AD%25E8%258F%25AF%25E9%259B%25BB%25E4%25BF%25A1adr1%25E6%2597%25A5%25E4%25B8%258A%25E6%25BC%25B20-15%25E7%25BE%258E%25E5%2585%2583%25E6%25BC%25B2%25E5%25B9%25850-36-%25E6%258A%2598%25E5%258F%25B0%25E8%2582%25A1135-43%25E5%2585%2583-215119490.html&ct=ga&cd=CAIyHWVhMjk0Y2MzNjllNDk5OGE6Y29tOnpoLVRXOlRX&usg=AOvVaw1H8C7Ok1XiSqF-7LN2KM_b",
    "published": "2026-04-01T22:07:41Z",
    "summary": "<b>中華電</b>. <b>2412</b>.TW. 134.0(0.75%). (中央社台北2026年4月2日電)中華電信在NYSE掛牌ADR 以42.39美元作收，上漲0.15美元，漲幅0.36%。 由於每單位中華電信ADR相當於&nbsp;...",
    "stock_id": "2412",
    "name": "中華電",
    "fetched_at": "2026-04-02T16:04:43.980857+00:00"
  },
  {
    "id": "tag:google.com,2013:googlealerts/feed:17506739882593590374",
    "title": "LINE帳號被盜怎麼辦？ 事前防範與自救方式一次看",
    "link": "https://www.google.com/url?rct=j&sa=t&url=https://news.pchome.com.tw/finance/cna_business/20260402/index-17751356675706522003.html&ct=ga&cd=CAIyHWVhMjk0Y2MzNjllNDk5OGE6Y29tOnpoLVRXOlRX&usg=AOvVaw0Pnk9PuFxLbmnubh_LsaHd",
    "published": "2026-04-02T13:27:30Z",
    "summary": "各電信業者雖表示尚未證實兩者具直接關聯，但仍迅速提出因應措施，以降低風險與客服壓力。 業者建議，用戶可自行透過簡易方式關閉語音信箱，例如<b>中華電</b>（<b>2412</b>）用戶於&nbsp;...",
    "stock_id": "2412",
    "name": "中華電",
    "fetched_at": "2026-04-02T19:52:21.456515+00:00"
  },
  {
    "id": "tag:google.com,2013:googlealerts/feed:12516458378882585668",
    "title": "3045 台灣大- 川普演說：提油救火；信用破產，油價大漲- 股市爆料同學會",
    "link": "https://www.google.com/url?rct=j&sa=t&url=http://www.cmoney.tw/forum/article/177887896&ct=ga&cd=CAIyHWVhMjk0Y2MzNjllNDk5OGE6Y29tOnpoLVRXOlRX&usg=AOvVaw0weEK17ZiDp_TIRchgzA9G",
    "published": "2026-04-02T13:21:54Z",
    "summary": "<b>中華電</b>. <b>2412</b>. 134. 0. (0%) &middot; 遠傳. 4904. 92.5. 1. (-1.07%). Scroll right. 發文者 ... <b>中華電</b> &middot; 遠傳. 展開 +3. 川普演說：提油救火；信用破產，油價大漲.",
    "stock_id": "2412",
    "name": "中華電",
    "fetched_at": "2026-04-02T19:52:21.456526+00:00"
  },
  {
    "id": "tag:google.com,2013:googlealerts/feed:12047923786242124938",
    "title": "中鋼紀念品被罵翻「飯糰都買不起」 他趁失望賣壓：一口氣買200張 - 東森財經新聞",
    "link": "https://www.google.com/url?rct=j&sa=t&url=https://fnc.ebc.net.tw/fncnews/stock/208593&ct=ga&cd=CAIyHWVhMjk0Y2MzNjllNDk5OGE6Y29tOnpoLVRXOlRX&usg=AOvVaw1GQWmf5qk5rEbyYmXOkrL4",
    "published": "2026-04-02T22:35:03Z",
    "summary": "... <b>中華電</b>(<b>2412</b>)致力打造國家級AI基礎設施等三大目標. 台股. (2025年8月27日). PR. 旅行花費難預測？全包式假期不只幫你省預算更省精力！ PR・Club Med Taiwan.",
    "stock_id": "2412",
    "name": "中華電",
    "fetched_at": "2026-04-02T23:40:24.199353+00:00"
  },
  {
    "id": "tag:google.com,2013:googlealerts/feed:18083924138239416894",
    "title": "<b>2412 中華電</b>- 電信搶攻兒童智慧手表商機 - 理財寶",
    "link": "https://www.google.com/url?rct=j&sa=t&url=https://www.cmoney.tw/forum/article/177893674&ct=ga&cd=CAIyHWVhMjk0Y2MzNjllNDk5OGE6Y29tOnpoLVRXOlRX&usg=AOvVaw1feq0ZZIouU1ByNDPSlqsc",
    "published": "2026-04-02T22:29:30Z",
    "summary": "心得：<b>中華電</b>也來賣娃娃手錶，真能賺多久？---中華電信（<b>2412</b>）在兒童節前夕，瞄準新的潛在客群──兒童及其家長，推出了一系列兒童智慧手表的促銷活動。這次的策略.",
    "stock_id": "2412",
    "name": "中華電",
    "fetched_at": "2026-04-02T23:40:24.199363+00:00"
  },
  {
    "id": "tag:google.com,2013:googlealerts/feed:10895107057079043865",
    "title": "LINE帳號被盜怎麼辦？事前防範與自救方式一次看 - 理財寶",
    "link": "https://www.google.com/url?rct=j&sa=t&url=https://www.cmoney.tw/forum/article/177889855&ct=ga&cd=CAIyHWVhMjk0Y2MzNjllNDk5OGE6Y29tOnpoLVRXOlRX&usg=AOvVaw2HwohaDtXaiBmNkKCjfvFC",
    "published": "2026-04-02T18:16:02Z",
    "summary": "<b>中華電</b>. <b>2412</b>. -. -. (-) &middot; 遠傳. 4904. -. -. (-). Scroll right. 發文者頭像 &middot; UDN ... <b>中華電</b>. <b>2412</b>. -. 0. 台股最新. 17 小時前 投資網誌. 連華爾街都盯上的台&nbsp;...",
    "stock_id": "2412",
    "name": "中華電",
    "fetched_at": "2026-04-02T23:40:24.199368+00:00"
  },
  {
    "id": "tag:google.com,2013:googlealerts/feed:6495252155586572239",
    "title": "填補海纜法制真空！數發部建立破壞鑑定標準、反制灰區攻擊",
    "link": "https://www.google.com/url?rct=j&sa=t&url=https://www.cmoney.tw/forum/article/177897645&ct=ga&cd=CAIyHWVhMjk0Y2MzNjllNDk5OGE6Y29tOnpoLVRXOlRX&usg=AOvVaw0gb1X5f3Wm5mlMcVnQtllB",
    "published": "2026-04-03T06:17:16Z",
    "summary": "<b>中華電</b>. 展開 +1. 填補海纜法制真空！數發部建立破壞鑑定標準、反制灰區攻擊 ... <b>2412</b>. 134. 0. 最新時事. 2 天前 投資網誌. 【即時新聞】中華電信最新推出&nbsp;...",
    "stock_id": "2412",
    "name": "中華電",
    "fetched_at": "2026-04-03T08:04:30.280856+00:00"
  },
  {
    "id": "tag:google.com,2013:googlealerts/feed:1319853219158643932",
    "title": "LINE盜用事件引爆「關閉語音信箱之亂」！台灣大、中華電信、遠傳緊急因應",
    "link": "https://www.google.com/url?rct=j&sa=t&url=https://www.cmoney.tw/forum/article/177893155&ct=ga&cd=CAIyHWVhMjk0Y2MzNjllNDk5OGE6Y29tOnpoLVRXOlRX&usg=AOvVaw1mefkzbYtQFipWlc-CgLgx",
    "published": "2026-04-03T03:18:47Z",
    "summary": "遠傳. 4904. 92.5. 1. (-1.07%) &middot; <b>中華電</b>. <b>2412</b>. 134. 0. (0%).",
    "stock_id": "2412",
    "name": "中華電",
    "fetched_at": "2026-04-03T08:04:30.280867+00:00"
  },
  {
    "id": "tag:google.com,2013:googlealerts/feed:1300166320847669674",
    "title": "中華電信ADR2日上漲0.02美元漲幅0.05%折台股135.59元 - Yahoo股市",
    "link": "https://www.google.com/url?rct=j&sa=t&url=https://tw.stock.yahoo.com/news/%25E4%25B8%25AD%25E8%258F%25AF%25E9%259B%25BB%25E4%25BF%25A1adr2%25E6%2597%25A5%25E4%25B8%258A%25E6%25BC%25B20-02%25E7%25BE%258E%25E5%2585%2583%25E6%25BC%25B2%25E5%25B9%25850-05-%25E6%258A%2598%25E5%258F%25B0%25E8%2582%25A1135-59%25E5%2585%2583-011121535.html&ct=ga&cd=CAIyHWVhMjk0Y2MzNjllNDk5OGE6Y29tOnpoLVRXOlRX&usg=AOvVaw3aaOMkOMTLUSpb4CGPo-qh",
    "published": "2026-04-03T01:39:18Z",
    "summary": "<b>中華電</b>. <b>2412</b>.TW. 134.0(0.00%). (中央社台北2026年4月3日電)中華電信在NYSE掛牌ADR 以42.41美元作收，上漲0.02美元，漲幅0.05%。 由於每單位中華電信ADR相當於&nbsp;...",
    "stock_id": "2412",
    "name": "中華電",
    "fetched_at": "2026-04-03T08:04:30.280872+00:00"
  }
]