[
  {
    "id": "tag:google.com,2013:googlealerts/feed:14417234089196182835",
    "title": "<b>精誠6214</b>當日股價走勢_個股_台股 - 富聯網",
    "link": "https://www.google.com/url?rct=j&sa=t&url=https://ww2.money-link.com.tw/TWStock/StockChart.aspx%3FSymId%3D08544U&ct=ga&cd=CAIyHWI5OWFhMzZmZjA5NDMyZGM6Y29tOnpoLVRXOlRX&usg=AOvVaw3VnYR3-qeWPiuD-PlfYKnT",
    "published": "2026-03-05T18:25:35Z",
    "summary": "富聯網讓你看懂最完整的台股<b>精誠</b>(<b>6214</b>)個股總覽資訊。台股最即時、最完整的台股走勢圖，財經專家讓您一分鐘看懂台股。全方位選股工具，當日大盤、個股、興櫃、&nbsp;...",
    "stock_id": "6214",
    "name": "精誠",
    "fetched_at": "2026-03-07T03:19:20.376139+00:00"
  },
  {
    "id": "tag:google.com,2013:googlealerts/feed:7205717743286645314",
    "title": "(<b>6214</b>) <b>精誠</b>- 董事、監察人及內部關係人持股明細- 黃大倫(獨立董事本人)",
    "link": "https://www.google.com/url?rct=j&sa=t&url=https://goodinfo.tw/tw/StockDirectorShareholdDetail.asp%3FSTOCK_ID%3D6214%26RPT_MONTH%3D202603%26JOB_TITLE%3D%25E7%258D%25A8%25E7%25AB%258B%25E8%2591%25A3%25E4%25BA%258B%25E6%259C%25AC%25E4%25BA%25BA%26NAME%3D%25E9%25BB%2583%25E5%25A4%25A7%25E5%2580%25AB%26STEP%3D2&ct=ga&cd=CAIyHWI5OWFhMzZmZjA5NDMyZGM6Y29tOnpoLVRXOlRX&usg=AOvVaw1kROoQbizoYkBuVrJU4jB3",
    "published": "2026-03-04T21:56:54Z",
    "summary": "<b>6214 精誠</b>/ 董監持股/ 持股明細. <b>6214 精誠</b> &middot; 權證標的 資料日期: 03/04. 成交價, 昨收, 漲跌價 &middot; 漲跌幅 &middot; 振幅, 開盤, 最高, 最低. 108.5, 112, -3.5, -3.12%&nbsp;...",
    "stock_id": "6214",
    "name": "精誠",
    "fetched_at": "2026-03-07T03:19:20.376150+00:00"
  },
  {
    "id": "tag:google.com,2013:googlealerts/feed:637294484755151047",
    "title": "(<b>6214</b>) <b>精誠</b>| 公告本公司董事會決議召開115年股東常會相關事宜(召開方式:視訊輔助股東會)",
    "link": "https://www.google.com/url?rct=j&sa=t&url=https://www.opendata.vip/stocks/listedCompanyNewsInfo/17985&ct=ga&cd=CAIyHWI5OWFhMzZmZjA5NDMyZGM6Y29tOnpoLVRXOlRX&usg=AOvVaw2x9gr7szmfVTajIFCtlgNf",
    "published": "2026-03-04T20:15:32Z",
    "summary": "(<b>6214</b>) <b>精誠</b>| 公告本公司董事會決議召開115年股東常會相關事宜(召開方式:視訊輔助股東會). （<b>6214</b>）<b>精誠</b>｜ 公告本公司董事會決議召開115年股東常會相關&nbsp;...",
    "stock_id": "6214",
    "name": "精誠",
    "fetched_at": "2026-03-07T03:19:20.376156+00:00"
  }
]