[
  {
    "id": "tag:google.com,2013:googlealerts/feed:6710807551828704112",
    "title": "電支業務靚<b>LINEPAY</b>衝業界第一- 證券．權證 - 中時新聞網",
    "link": "https://www.google.com/url?rct=j&sa=t&url=https://www.chinatimes.com/newspapers/20260320000371-260206&ct=ga&cd=CAIyHWZhNWM5ODYwNDEyNDdjZmE6Y29tOnpoLVRXOlRX&usg=AOvVaw2ZM_69hr4gl0r0maRZWj_H",
    "published": "2026-03-20T08:34:11Z",
    "summary": "第三方支付龍頭<b>LINEPAY</b>（<b>7722</b>）19日舉辦法說會，該公司首度揭露旗下電子支付事業LINE Pay Money經營成果，電支業務上線迄今不到四個月，用戶數逾300萬人，其中，&nbsp;...",
    "stock_id": "7722",
    "name": "LINEPAY",
    "fetched_at": "2026-03-21T19:30:22.103700+00:00"
  }
]